{
  "page": "东隅",
  "latest_rev_id": "20260424-103829-ce9c1c",
  "revision_count": 3,
  "revisions": [
    {
      "rev_id": "20260424-103829-ce9c1c",
      "timestamp": "2026-04-24T10:38:29Z",
      "author": "butler",
      "summary": "butler/rebuild-place-citations: 重建PN引文节",
      "parent_rev": "20260424-073301-b6ee55",
      "content_hash": "sha256:ce9c1ce16ecffb1e262289984ded5151d165d21d88cfd6909ed15a1e1dab253a",
      "size": 317,
      "content": "---\nid: 东隅\ntype: place\nlabel: 东隅\naliases: []\ntags: [\"地名\", \"区域\"]\nauto_generated: true\n---\n\n# 东隅\n\n## 史记引文\n\n《史记》中出现 **1** 次，见于以下章节：\n\n- [[114_东越列传]]：`12`\n\n**引文摘录：**\n\n> **出自 [[114_东越列传]]（12）：** 句践之裔，是曰无诸。"
    },
    {
      "rev_id": "20260424-073301-b6ee55",
      "timestamp": "2026-04-24T07:33:01Z",
      "author": "butler",
      "summary": "butler/rebuild-place-citations: 重建PN引文节",
      "parent_rev": "20260424-070249-8fcfa4",
      "content_hash": "sha256:b6ee5581acb3bac902776b6b9e31cdd83782e3e9196f2f0e2556d7e602cf52b0",
      "size": 314,
      "content": "---\nid: 东隅\ntype: place\nlabel: 东隅\naliases: []\ntags: [\"地名\", \"区域\"]\nauto_generated: true\n---\n\n# 东隅\n\n## 史记引文\n\n《史记》中出现 **1** 次，见于以下章节：\n\n- [[114_东越列传]]：`12`\n\n**引文摘录：**\n\n出自 [[114_东越列传]]（12）：\n> 句践之裔，是曰无诸。\n"
    },
    {
      "rev_id": "20260424-070249-8fcfa4",
      "timestamp": "2026-04-24T07:02:49Z",
      "author": "butler",
      "summary": "butler/import-places: 新建地名页",
      "parent_rev": null,
      "content_hash": "sha256:8fcfa497564dcd241b271e64cfd8384f063c53d58d4c62f5277a4244788ced40",
      "size": 211,
      "content": "---\nid: 东隅\ntype: place\nlabel: 东隅\naliases: []\ntags: [\"地名\", \"区域\"]\nauto_generated: true\n---\n\n# 东隅\n\n## 史记引文\n\n《史记》中出现 **1** 次，见于以下章节：\n\n[[114_东越列传]]\n"
    }
  ]
}
