{
  "page": "中岳",
  "latest_rev_id": "20260424-070250-eb78c8",
  "revision_count": 1,
  "revisions": [
    {
      "rev_id": "20260424-070250-eb78c8",
      "timestamp": "2026-04-24T07:02:50Z",
      "author": "butler",
      "summary": "butler/import-places: 新建地名页",
      "parent_rev": null,
      "content_hash": "sha256:eb78c8099509abc05ebbe5f1c7adabcdb10f71379011e42bc4d3169539722400",
      "size": 847,
      "content": "---\nid: 中岳\ntype: place\nlabel: 中岳\naliases: []\ntags: [\"地名\", \"山脉\"]\nauto_generated: true\n---\n\n# 中岳\n\n## 史记引文\n\n《史记》中出现 **6** 次，见于以下章节：\n\n[[012_孝武本纪]]  [[028_封禅书]]  [[117_司马相如列传]]\n\n**引文摘录：**\n\n出自 [[012_孝武本纪]]（30.1）：\n> 封泰山 三月，遂东幸缑氏，礼登中岳太室。 从官在山下闻若有言“万岁” 云。\n\n出自 [[028_封禅书]]：\n> 也。 十一月，巡狩至北岳。 北岳，恆山也。 皆如岱宗之礼。 中岳，嵩高也。 五载 禹遵之。後十四世，至帝孔甲，淫德\n\n出自 [[117_司马相如列传]]：\n> 奉符以行事，不为进越。故圣王弗替，而修礼地祇，谒款天神，勒功中岳，以彰至尊，舒盛德，发号荣，受厚福，以浸黎民也。皇皇哉斯事！\n"
    }
  ]
}
