{
  "page": "假途灭虢",
  "latest_rev_id": "20260425-144036-676efe",
  "revision_count": 1,
  "revisions": [
    {
      "rev_id": "20260425-144036-676efe",
      "timestamp": "2026-04-25T14:40:36Z",
      "author": "butler",
      "summary": "H2: 从史记引文推导相关章节节",
      "parent_rev": null,
      "content_hash": "sha256:676efef95e4b8e107ace60410035f6a86ea18595feda59cb63eb9d6d1a841aa5",
      "size": 1102,
      "content": "---\nid: 假途灭虢\ntype: chengyu\nlabel: 假途灭虢\naliases: []\ntags: [\"史记\", \"成语\", \"典故\", \"晋世家\"]\nsources: [\"晋世家\"]\ndescription: \"以借路为名行灭国之实\"\nfeatured: false\n---\n\n# 假途灭虢\n\n**释义**：以借路为名行灭国之实\n\n出自《史记》，见于[[039_晋世家|晋世家]]。\n\n## 史记原文\n\n出自 [[039_晋世家|晋世家]] （039-24.27）：\n\n> **原文出处**：使荀息以屈产之乘假道於虞…遂伐虢\n> **上下文**：非太子之事也。师在制命而已，禀命则不威，专命则不孝，故君之嗣適不可以帅师。君失其官，率师不威，将安用之？\"公曰：\"寡人有子，未知其太子谁立。\"里克不对而退，见太子。太子曰：\"吾其废乎？\"里克曰：\"太子勉之！教以军旅，\"不共是惧，何故废乎？且子惧不孝，毋惧不得立。修己而不责人，则免於难。\"太子帅师，公衣之偏衣，佩之金玦。里克谢病，不从太子。太子遂伐东山。 [25.28] 十九年，献公曰：\"始吾先君庄…\n## 相关章节\n\n- [[039_晋世家|晋世家]]\n"
    }
  ]
}
