{
  "page": "公元前566年",
  "latest_rev_id": "20260425-154731-9db1e9",
  "revision_count": 6,
  "revisions": [
    {
      "rev_id": "20260425-154731-9db1e9",
      "timestamp": "2026-04-25T15:47:31Z",
      "author": "butler",
      "summary": "H6: featured",
      "parent_rev": "20260425-150548-914843",
      "content_hash": "sha256:9db1e94d2d57fefe0ed8be525d4ac94b4c07398321a49c224cd69f06ed68dac4",
      "size": 1098,
      "content": "featured: true\n---\nid: 公元前566年\ntype: year\nsources: [郑世家]\nlabel: 公元前566年\naliases: [\"周灵王六年\", \"鲁襄公七年\", \"齐灵公十六年\", \"晋悼公七年\", \"秦景公十一年\", \"楚共王二十五年\", \"宋平公十年\", \"卫献公十一年\", \"陈哀公三年\", \"蔡景侯二十六年\", \"曹成公十二年\", \"郑厘公五年\", \"燕武公八年\", \"吴寿梦二十年\"]\ntags: [编年]\ndescription: \"公元前566年大事：子驷弑釐公等\"\n---\n# 公元前566年\n\n## 各国纪年\n\n| 国 | 君主 | 年份 |\n|---|---|---|\n| 卫 | 卫献公 | 十一年 |\n| 吴 | 吴寿梦 | 二十年 |\n| 周 | 周灵王 | 六年 |\n| 宋 | 宋平公 | 十年 |\n| 晋 | 晋悼公 | 七年 |\n| 曹 | 曹成公 | 十二年 |\n| 楚 | 楚共王 | 二十五年 |\n| 燕 | 燕武公 | 八年 |\n| 秦 | 秦景公 | 十一年 |\n| 蔡 | 蔡景侯 | 二十六年 |\n| 郑 | 郑厘公 | 五年 |\n| 陈 | 陈哀公 | 三年 |\n| 鲁 | 鲁襄公 | 七年 |\n| 齐 | 齐灵公 | 十六年 |\n\n## 大事\n\n- [[子驷弑釐公]] `042-019` [[042_郑世家]]\n\n---\n\n## 相关章节\n\n- [[042_郑世家|郑世家]]\n"
    },
    {
      "rev_id": "20260425-150548-914843",
      "timestamp": "2026-04-25T15:05:48Z",
      "author": "butler",
      "summary": "H2: 从大事记推导相关章节节",
      "parent_rev": "20260425-142431-8769bd",
      "content_hash": "sha256:914843ebe0536f31e1f73682c438c2a546c057ca9ebf493c91b7ebe48f9e4c1c",
      "size": 1083,
      "content": "---\nid: 公元前566年\ntype: year\nsources: [郑世家]\nlabel: 公元前566年\naliases: [\"周灵王六年\", \"鲁襄公七年\", \"齐灵公十六年\", \"晋悼公七年\", \"秦景公十一年\", \"楚共王二十五年\", \"宋平公十年\", \"卫献公十一年\", \"陈哀公三年\", \"蔡景侯二十六年\", \"曹成公十二年\", \"郑厘公五年\", \"燕武公八年\", \"吴寿梦二十年\"]\ntags: [编年]\ndescription: \"公元前566年大事：子驷弑釐公等\"\n---\n# 公元前566年\n\n## 各国纪年\n\n| 国 | 君主 | 年份 |\n|---|---|---|\n| 卫 | 卫献公 | 十一年 |\n| 吴 | 吴寿梦 | 二十年 |\n| 周 | 周灵王 | 六年 |\n| 宋 | 宋平公 | 十年 |\n| 晋 | 晋悼公 | 七年 |\n| 曹 | 曹成公 | 十二年 |\n| 楚 | 楚共王 | 二十五年 |\n| 燕 | 燕武公 | 八年 |\n| 秦 | 秦景公 | 十一年 |\n| 蔡 | 蔡景侯 | 二十六年 |\n| 郑 | 郑厘公 | 五年 |\n| 陈 | 陈哀公 | 三年 |\n| 鲁 | 鲁襄公 | 七年 |\n| 齐 | 齐灵公 | 十六年 |\n\n## 大事\n\n- [[子驷弑釐公]] `042-019` [[042_郑世家]]\n\n---\n\n## 相关章节\n\n- [[042_郑世家|郑世家]]\n"
    },
    {
      "rev_id": "20260425-142431-8769bd",
      "timestamp": "2026-04-25T14:24:31Z",
      "author": "butler",
      "summary": "H4: 补全年份页description字段",
      "parent_rev": "20260425-120615-87c056",
      "content_hash": "sha256:8769bd554abcbfb052f675b527364f4f1495b9ec78c753ccac3c21bcd823d8fb",
      "size": 1030,
      "content": "---\nid: 公元前566年\ntype: year\nsources: [郑世家]\nlabel: 公元前566年\naliases: [\"周灵王六年\", \"鲁襄公七年\", \"齐灵公十六年\", \"晋悼公七年\", \"秦景公十一年\", \"楚共王二十五年\", \"宋平公十年\", \"卫献公十一年\", \"陈哀公三年\", \"蔡景侯二十六年\", \"曹成公十二年\", \"郑厘公五年\", \"燕武公八年\", \"吴寿梦二十年\"]\ntags: [编年]\ndescription: \"公元前566年大事：子驷弑釐公等\"\n---\n# 公元前566年\n\n## 各国纪年\n\n| 国 | 君主 | 年份 |\n|---|---|---|\n| 卫 | 卫献公 | 十一年 |\n| 吴 | 吴寿梦 | 二十年 |\n| 周 | 周灵王 | 六年 |\n| 宋 | 宋平公 | 十年 |\n| 晋 | 晋悼公 | 七年 |\n| 曹 | 曹成公 | 十二年 |\n| 楚 | 楚共王 | 二十五年 |\n| 燕 | 燕武公 | 八年 |\n| 秦 | 秦景公 | 十一年 |\n| 蔡 | 蔡景侯 | 二十六年 |\n| 郑 | 郑厘公 | 五年 |\n| 陈 | 陈哀公 | 三年 |\n| 鲁 | 鲁襄公 | 七年 |\n| 齐 | 齐灵公 | 十六年 |\n\n## 大事\n\n- [[子驷弑釐公]] `042-019` [[042_郑世家]]\n"
    },
    {
      "rev_id": "20260425-120615-87c056",
      "timestamp": "2026-04-25T12:06:15Z",
      "author": "butler",
      "summary": "H4: sources=[郑世家]（from wikilink）",
      "parent_rev": "20260424-064210-b8aa46",
      "content_hash": "sha256:87c0563c7b588f7f8765ce8fd1b422bcced45a601598e843fc748e8fca29a3b0",
      "size": 973,
      "content": "---\nid: 公元前566年\ntype: year\nsources: [郑世家]\nlabel: 公元前566年\naliases: [\"周灵王六年\", \"鲁襄公七年\", \"齐灵公十六年\", \"晋悼公七年\", \"秦景公十一年\", \"楚共王二十五年\", \"宋平公十年\", \"卫献公十一年\", \"陈哀公三年\", \"蔡景侯二十六年\", \"曹成公十二年\", \"郑厘公五年\", \"燕武公八年\", \"吴寿梦二十年\"]\ntags: [编年]\n---\n\n# 公元前566年\n\n## 各国纪年\n\n| 国 | 君主 | 年份 |\n|---|---|---|\n| 卫 | 卫献公 | 十一年 |\n| 吴 | 吴寿梦 | 二十年 |\n| 周 | 周灵王 | 六年 |\n| 宋 | 宋平公 | 十年 |\n| 晋 | 晋悼公 | 七年 |\n| 曹 | 曹成公 | 十二年 |\n| 楚 | 楚共王 | 二十五年 |\n| 燕 | 燕武公 | 八年 |\n| 秦 | 秦景公 | 十一年 |\n| 蔡 | 蔡景侯 | 二十六年 |\n| 郑 | 郑厘公 | 五年 |\n| 陈 | 陈哀公 | 三年 |\n| 鲁 | 鲁襄公 | 七年 |\n| 齐 | 齐灵公 | 十六年 |\n\n## 大事\n\n- [[子驷弑釐公]] `042-019` [[042_郑世家]]\n"
    },
    {
      "rev_id": "20260424-064210-b8aa46",
      "timestamp": "2026-04-24T06:42:10Z",
      "author": "butler",
      "summary": "butler/linkify-events: 事件名转 wiki 链接",
      "parent_rev": "20260424-063332-9c07fc",
      "content_hash": "sha256:b8aa467ea407ac4bea29c8e5708fbecbe1084de8982b221694a8c4b8ac728aad",
      "size": 952,
      "content": "---\nid: 公元前566年\ntype: year\nlabel: 公元前566年\naliases: [\"周灵王六年\", \"鲁襄公七年\", \"齐灵公十六年\", \"晋悼公七年\", \"秦景公十一年\", \"楚共王二十五年\", \"宋平公十年\", \"卫献公十一年\", \"陈哀公三年\", \"蔡景侯二十六年\", \"曹成公十二年\", \"郑厘公五年\", \"燕武公八年\", \"吴寿梦二十年\"]\ntags: [编年]\n---\n\n# 公元前566年\n\n## 各国纪年\n\n| 国 | 君主 | 年份 |\n|---|---|---|\n| 卫 | 卫献公 | 十一年 |\n| 吴 | 吴寿梦 | 二十年 |\n| 周 | 周灵王 | 六年 |\n| 宋 | 宋平公 | 十年 |\n| 晋 | 晋悼公 | 七年 |\n| 曹 | 曹成公 | 十二年 |\n| 楚 | 楚共王 | 二十五年 |\n| 燕 | 燕武公 | 八年 |\n| 秦 | 秦景公 | 十一年 |\n| 蔡 | 蔡景侯 | 二十六年 |\n| 郑 | 郑厘公 | 五年 |\n| 陈 | 陈哀公 | 三年 |\n| 鲁 | 鲁襄公 | 七年 |\n| 齐 | 齐灵公 | 十六年 |\n\n## 大事\n\n- [[子驷弑釐公]] `042-019` [[042_郑世家]]\n"
    },
    {
      "rev_id": "20260424-063332-9c07fc",
      "timestamp": "2026-04-24T06:33:32Z",
      "author": "butler",
      "summary": "butler/import-chronology: 导入编年事件",
      "parent_rev": null,
      "content_hash": "sha256:9c07fc6a4c447ad7875c8724b53d9ead87f7444075a61ac0e59398534d78347b",
      "size": 948,
      "content": "---\nid: 公元前566年\ntype: year\nlabel: 公元前566年\naliases: [\"周灵王六年\", \"鲁襄公七年\", \"齐灵公十六年\", \"晋悼公七年\", \"秦景公十一年\", \"楚共王二十五年\", \"宋平公十年\", \"卫献公十一年\", \"陈哀公三年\", \"蔡景侯二十六年\", \"曹成公十二年\", \"郑厘公五年\", \"燕武公八年\", \"吴寿梦二十年\"]\ntags: [编年]\n---\n\n# 公元前566年\n\n## 各国纪年\n\n| 国 | 君主 | 年份 |\n|---|---|---|\n| 卫 | 卫献公 | 十一年 |\n| 吴 | 吴寿梦 | 二十年 |\n| 周 | 周灵王 | 六年 |\n| 宋 | 宋平公 | 十年 |\n| 晋 | 晋悼公 | 七年 |\n| 曹 | 曹成公 | 十二年 |\n| 楚 | 楚共王 | 二十五年 |\n| 燕 | 燕武公 | 八年 |\n| 秦 | 秦景公 | 十一年 |\n| 蔡 | 蔡景侯 | 二十六年 |\n| 郑 | 郑厘公 | 五年 |\n| 陈 | 陈哀公 | 三年 |\n| 鲁 | 鲁襄公 | 七年 |\n| 齐 | 齐灵公 | 十六年 |\n\n## 大事\n\n- 子驷弑釐公 `042-019` [[042_郑世家]]\n"
    }
  ]
}
