{
  "page": "商祝",
  "latest_rev_id": "20260426-092011-b7df72",
  "revision_count": 5,
  "revisions": [
    {
      "rev_id": "20260426-092011-b7df72",
      "timestamp": "2026-04-26T09:20:11Z",
      "author": "butler",
      "summary": "sanjia-entity: 追加三家注 5 条",
      "parent_rev": "20260425-154711-4dba35",
      "content_hash": "sha256:b7df7292ddae4084c2f9130cfbd80f214558ba67ad7df5846c21d4bfc0914cb0",
      "size_before": 783,
      "size": 2379,
      "content": "---\nid: 商祝\ntype: official\nlabel: 商祝\naliases: []\ncanonical_name: 商祝\ntags: [\"官职\", \"上古官\"]\ndescription: \"《史记》中的官职（上古官），出现于《史记》1处\"\nsources: [乐书]\nquality: basic\n---\n# 商祝\n\n出现于《史记》**1** 处。\n\n## 史记引文\n\n《史记》中出现 **1** 处。\n\n**章节分布：**\n\n- [[024_乐书|乐书]]：（024-12.15）\n\n**引文摘录：**\n\n> 出自 [[024_乐书|乐书]] （024-12.15）：…升降为礼者，礼之末节也，故有司掌之。乐师辩乎声诗，故北面而弦；宗祝辩乎宗庙之礼，故後尸；**商祝**辩乎丧礼，故後主人。是故德成而上，艺成而下；行成而先，事成而後。是故先王有上有下，有先有…\n## 相关章节\n\n- [[024_乐书|乐书]]\n\n## 三家注\n\n以下是《史记》三家注中直接注释「商祝」相关文字的条目。\n\n#### 出自 [[024_乐书]]\n\n##### n255 · 「……庙之礼，故后尸；商祝辩乎丧礼，**商祝辩乎丧礼，**故后主人。……」\n\n> **【集解】** 郑玄曰：「商祝，祝习商礼者，商人教以敬于接神。」\n\n##### n256 · 「……后尸；商祝辩乎丧礼，故后主人。**故后主人。**是故德成而上，……」\n\n> **【正义】** 商祝者，殷商之神祝，习商家神礼以相佐丧事，故云辩丧礼。其虽掌丧事而非发丧之主，故在主人后，言立处贱也。\n\n##### n257 · 「……丧礼，故后主人。是故德成而上，**是故德成而上，**蓺成而下；……」\n\n> **【正义】** 上谓堂上也。德成谓人君礼乐德成则为君，故居堂上，南面，尊之也。\n\n##### n260 · 「……蓺成而下；行成而先，事成而后。**事成而后。**是故先王有上有下，有先有后，然后可以有制……」\n\n> **【集解】** 郑玄曰：「德，三德也。行，三行也。蓺，才伎也。先谓位在上也，后谓位在下也。」\n>\n> **【正义】** 事为劣，故为在宗、商二祝也。识尸及主人后也。\n\n##### n261 · 「……先有后，然后可以有制于天下也。**上有下，有先有后，然后可以有制于天下也。**……」\n\n> **【集解】** 郑玄曰：「言尊卑备，乃可制作以为治。」\n>\n> **【正义】** 故先王使上下前后尊卑分，乃可制礼作乐，以班于天下也。如周公六年乃为礼也。\n\n"
    },
    {
      "rev_id": "20260425-154711-4dba35",
      "timestamp": "2026-04-25T15:47:11Z",
      "author": "butler",
      "summary": "H6: featured",
      "parent_rev": "20260425-144211-50b0bd",
      "content_hash": "sha256:4dba35ac4c425780fd6d3eeb628e205bf8b3014b5a5cb144de77a7e07988f83b",
      "size": 783,
      "content": "---\nid: 商祝\ntype: official\nlabel: 商祝\naliases: []\ncanonical_name: 商祝\ntags: [\"官职\", \"上古官\"]\nfeatured: true\ndescription: \"《史记》中的官职（上古官），出现于《史记》1处\"\nsources: [乐书]\n---\n# 商祝\n\n出现于《史记》**1** 处。\n\n## 史记引文\n\n《史记》中出现 **1** 处。\n\n**章节分布：**\n\n- [[024_乐书|乐书]]：（024-12.15）\n\n**引文摘录：**\n\n> 出自 [[024_乐书|乐书]] （024-12.15）：…升降为礼者，礼之末节也，故有司掌之。乐师辩乎声诗，故北面而弦；宗祝辩乎宗庙之礼，故後尸；**商祝**辩乎丧礼，故後主人。是故德成而上，艺成而下；行成而先，事成而後。是故先王有上有下，有先有…\n## 相关章节\n\n- [[024_乐书|乐书]]\n",
      "size_before": 784
    },
    {
      "rev_id": "20260425-144211-50b0bd",
      "timestamp": "2026-04-25T14:42:11Z",
      "author": "butler",
      "summary": "H2: 从史记引文推导相关章节节",
      "parent_rev": "20260425-141553-e2074c",
      "content_hash": "sha256:50b0bd31ef796dcdc6bd4bce9d13c710e564547dc9871e07c8c9597963357c36",
      "size": 784,
      "content": "---\nid: 商祝\ntype: official\nlabel: 商祝\naliases: []\ncanonical_name: 商祝\ntags: [\"官职\", \"上古官\"]\nfeatured: false\ndescription: \"《史记》中的官职（上古官），出现于《史记》1处\"\nsources: [乐书]\n---\n# 商祝\n\n出现于《史记》**1** 处。\n\n## 史记引文\n\n《史记》中出现 **1** 处。\n\n**章节分布：**\n\n- [[024_乐书|乐书]]：（024-12.15）\n\n**引文摘录：**\n\n> 出自 [[024_乐书|乐书]] （024-12.15）：…升降为礼者，礼之末节也，故有司掌之。乐师辩乎声诗，故北面而弦；宗祝辩乎宗庙之礼，故後尸；**商祝**辩乎丧礼，故後主人。是故德成而上，艺成而下；行成而先，事成而後。是故先王有上有下，有先有…\n## 相关章节\n\n- [[024_乐书|乐书]]\n",
      "size_before": 761
    },
    {
      "rev_id": "20260425-141553-e2074c",
      "timestamp": "2026-04-25T14:15:53Z",
      "author": "butler",
      "summary": "H4: 从引文章节链接推导sources字段",
      "parent_rev": "20260425-140544-8a474b",
      "content_hash": "sha256:e2074c65cdcb17000a57b4826fee0d55ad346a8b6fa977fba02d78b5c9a30e74",
      "size": 761,
      "content": "---\nid: 商祝\ntype: official\nlabel: 商祝\naliases: []\ncanonical_name: 商祝\ntags: [\"官职\", \"上古官\"]\nfeatured: false\ndescription: \"《史记》中的官职（上古官），出现于《史记》1处\"\nsources: [乐书]\n---\n# 商祝\n\n出现于《史记》**1** 处。\n\n## 史记引文\n\n《史记》中出现 **1** 处。\n\n**章节分布：**\n\n- [[024_乐书|乐书]]：（024-12.15）\n\n**引文摘录：**\n\n> 出自 [[024_乐书|乐书]] （024-12.15）：…升降为礼者，礼之末节也，故有司掌之。乐师辩乎声诗，故北面而弦；宗祝辩乎宗庙之礼，故後尸；**商祝**辩乎丧礼，故後主人。是故德成而上，艺成而下；行成而先，事成而後。是故先王有上有下，有先有…\n\n## 相关页面\n\n",
      "size_before": 743
    },
    {
      "rev_id": "20260425-140544-8a474b",
      "timestamp": "2026-04-25T14:05:44Z",
      "author": "butler",
      "summary": "H4: 补全实体词条description字段",
      "parent_rev": null,
      "content_hash": "sha256:8a474b7e73e65e406d9504b1da439ee1d62416176dc426fa4f5bfa2fa801df4d",
      "size": 743,
      "content": "---\nid: 商祝\ntype: official\nlabel: 商祝\naliases: []\ncanonical_name: 商祝\ntags: [\"官职\", \"上古官\"]\nfeatured: false\ndescription: \"《史记》中的官职（上古官），出现于《史记》1处\"\n---\n# 商祝\n\n出现于《史记》**1** 处。\n\n## 史记引文\n\n《史记》中出现 **1** 处。\n\n**章节分布：**\n\n- [[024_乐书|乐书]]：（024-12.15）\n\n**引文摘录：**\n\n> 出自 [[024_乐书|乐书]] （024-12.15）：…升降为礼者，礼之末节也，故有司掌之。乐师辩乎声诗，故北面而弦；宗祝辩乎宗庙之礼，故後尸；**商祝**辩乎丧礼，故後主人。是故德成而上，艺成而下；行成而先，事成而後。是故先王有上有下，有先有…\n\n## 相关页面\n\n",
      "size_before": 0
    }
  ]
}
