{
  "page": "处死",
  "latest_rev_id": "20260425-141616-a4a6b8",
  "revision_count": 2,
  "revisions": [
    {
      "rev_id": "20260425-141616-a4a6b8",
      "timestamp": "2026-04-25T14:16:16Z",
      "author": "butler",
      "summary": "H4: 从引文章节链接推导sources字段",
      "parent_rev": "20260425-140606-e6a524",
      "content_hash": "sha256:a4a6b8a10f9228cd569f242ea18730c9cc136dda21b141a1f4fde05805cda874",
      "size": 726,
      "content": "---\nid: 处死\ntype: legal\nlabel: 处死\naliases: []\ncanonical_name: 处死\ntags: [\"法律\"]\nfeatured: false\ndescription: \"《史记》中的法律术语（法律），出现于《史记》1处\"\nsources: [廉颇蔺相如列传]\n---\n# 处死\n\n出现于《史记》**1** 处。\n\n## 史记引文\n\n《史记》中出现 **1** 处。\n\n**章节分布：**\n\n- [[081_廉颇蔺相如列传|廉颇蔺相如列传]]：（081-38）\n\n**引文摘录：**\n\n> 出自 [[081_廉颇蔺相如列传|廉颇蔺相如列传]] （081-38）：太史公曰：知死必勇，非死者难也，**处死**者难。 方蔺相如引璧睨柱，及叱秦王左右，势不过诛，然士或怯懦而不敢发。 蔺相如一奋其气，…\n\n## 相关页面\n\n"
    },
    {
      "rev_id": "20260425-140606-e6a524",
      "timestamp": "2026-04-25T14:06:06Z",
      "author": "butler",
      "summary": "H4: 补全实体词条description字段",
      "parent_rev": null,
      "content_hash": "sha256:e6a524661a29ab53d6ee398889e0bc43894973da46a3ba97d55afed9952ad95f",
      "size": 693,
      "content": "---\nid: 处死\ntype: legal\nlabel: 处死\naliases: []\ncanonical_name: 处死\ntags: [\"法律\"]\nfeatured: false\ndescription: \"《史记》中的法律术语（法律），出现于《史记》1处\"\n---\n# 处死\n\n出现于《史记》**1** 处。\n\n## 史记引文\n\n《史记》中出现 **1** 处。\n\n**章节分布：**\n\n- [[081_廉颇蔺相如列传|廉颇蔺相如列传]]：（081-38）\n\n**引文摘录：**\n\n> 出自 [[081_廉颇蔺相如列传|廉颇蔺相如列传]] （081-38）：太史公曰：知死必勇，非死者难也，**处死**者难。 方蔺相如引璧睨柱，及叱秦王左右，势不过诛，然士或怯懦而不敢发。 蔺相如一奋其气，…\n\n## 相关页面\n\n"
    }
  ]
}
