{
  "page": "左庶长",
  "latest_rev_id": "20260425-153822-2bbbfe",
  "revision_count": 4,
  "revisions": [
    {
      "rev_id": "20260425-153822-2bbbfe",
      "timestamp": "2026-04-25T15:38:22Z",
      "author": "butler",
      "summary": "H6: featured",
      "parent_rev": "20260425-144346-4a0527",
      "content_hash": "sha256:2bbbfe37dd2453121206e53e41c073d4f11b69d49e0fc07c13af76836f3d5752",
      "size": 2167,
      "content": "---\nid: 左庶长\ntype: official\nlabel: 左庶长\naliases: []\ncanonical_name: 左庶长\ntags: [\"官职\", \"爵位\"]\nfeatured: true\ndescription: \"《史记》中的官职（爵位），出现于《史记》7处\"\nsources: [秦本纪, 平准书, 商君列传, 白起王翦列传]\n---\n# 左庶长\n\n出现于《史记》**7** 处。\n\n## 史记引文\n\n《史记》中出现 **7** 处。\n\n**章节分布：**\n\n- [[005_秦本纪|秦本纪]]：（005-51）\n- [[030_平准书|平准书]]：（030-24）、（030-46）\n- [[068_商君列传|商君列传]]：（068-3）\n- [[073_白起王翦列传|白起王翦列传]]：（073-1）、（073-4）\n- [[111_卫将军骠骑列传|卫将军骠骑列传]]：（111-50）\n\n**引文摘录（共 7 处，下列仅示 5 条）：**\n\n> 出自 [[005_秦本纪|秦本纪]] （005-51）：…公善之。甘龙、杜挚等弗然，相与争之。卒用卫鞅法，百姓苦之；居三年，百姓便之。乃拜卫鞅为**左庶长**。其事在商君语中。\n>\n> 出自 [[030_平准书|平准书]] （030-24）：天子乃思卜式之言，召拜卜式为中郎，爵**左庶长**，赐田十顷，布告天下，使明知之。 ## 卜式传记\n>\n> 出自 [[030_平准书|平准书]] （030-46）：…。时长之中，太仓、甘泉仓满。边馀穀诸物均输帛五百万匹。民不益赋而天下用饶。於是弘羊赐爵**左庶长**，黄金再百斤焉。 ## 卜式与桑弘羊的矛盾\n>\n> 出自 [[068_商君列传|商君列传]] （068-3）：…古而王，夏殷不易礼而亡。反古者不可非，而循礼者不足多。” 秦孝公曰：“善。” 以商鞅为**左庶长**，卒定变法之令。\n>\n> 出自 [[073_白起王翦列传|白起王翦列传]] （073-1）：白起者，郿人也。善用兵，事秦昭王。秦昭王十三年，而白起为**左庶长**，将而击韩之新城。是岁，魏冉相秦，举任鄙以为汉中守。其明年，白起为左更，攻韩、魏於伊阙…\n## 相关章节\n\n- [[005_秦本纪|秦本纪]]\n- [[030_平准书|平准书]]\n- [[068_商君列传|商君列传]]\n- [[073_白起王翦列传|白起王翦列传]]\n- [[111_卫将军骠骑列传|卫将军骠骑列传]]\n"
    },
    {
      "rev_id": "20260425-144346-4a0527",
      "timestamp": "2026-04-25T14:43:46Z",
      "author": "butler",
      "summary": "H2: 从史记引文推导相关章节节",
      "parent_rev": "20260425-141715-d48f0b",
      "content_hash": "sha256:4a05274c48760966e25e5268bac588c5362db325d0db45858af589f1829f83e3",
      "size": 2168,
      "content": "---\nid: 左庶长\ntype: official\nlabel: 左庶长\naliases: []\ncanonical_name: 左庶长\ntags: [\"官职\", \"爵位\"]\nfeatured: false\ndescription: \"《史记》中的官职（爵位），出现于《史记》7处\"\nsources: [秦本纪, 平准书, 商君列传, 白起王翦列传]\n---\n# 左庶长\n\n出现于《史记》**7** 处。\n\n## 史记引文\n\n《史记》中出现 **7** 处。\n\n**章节分布：**\n\n- [[005_秦本纪|秦本纪]]：（005-51）\n- [[030_平准书|平准书]]：（030-24）、（030-46）\n- [[068_商君列传|商君列传]]：（068-3）\n- [[073_白起王翦列传|白起王翦列传]]：（073-1）、（073-4）\n- [[111_卫将军骠骑列传|卫将军骠骑列传]]：（111-50）\n\n**引文摘录（共 7 处，下列仅示 5 条）：**\n\n> 出自 [[005_秦本纪|秦本纪]] （005-51）：…公善之。甘龙、杜挚等弗然，相与争之。卒用卫鞅法，百姓苦之；居三年，百姓便之。乃拜卫鞅为**左庶长**。其事在商君语中。\n>\n> 出自 [[030_平准书|平准书]] （030-24）：天子乃思卜式之言，召拜卜式为中郎，爵**左庶长**，赐田十顷，布告天下，使明知之。 ## 卜式传记\n>\n> 出自 [[030_平准书|平准书]] （030-46）：…。时长之中，太仓、甘泉仓满。边馀穀诸物均输帛五百万匹。民不益赋而天下用饶。於是弘羊赐爵**左庶长**，黄金再百斤焉。 ## 卜式与桑弘羊的矛盾\n>\n> 出自 [[068_商君列传|商君列传]] （068-3）：…古而王，夏殷不易礼而亡。反古者不可非，而循礼者不足多。” 秦孝公曰：“善。” 以商鞅为**左庶长**，卒定变法之令。\n>\n> 出自 [[073_白起王翦列传|白起王翦列传]] （073-1）：白起者，郿人也。善用兵，事秦昭王。秦昭王十三年，而白起为**左庶长**，将而击韩之新城。是岁，魏冉相秦，举任鄙以为汉中守。其明年，白起为左更，攻韩、魏於伊阙…\n## 相关章节\n\n- [[005_秦本纪|秦本纪]]\n- [[030_平准书|平准书]]\n- [[068_商君列传|商君列传]]\n- [[073_白起王翦列传|白起王翦列传]]\n- [[111_卫将军骠骑列传|卫将军骠骑列传]]\n"
    },
    {
      "rev_id": "20260425-141715-d48f0b",
      "timestamp": "2026-04-25T14:17:15Z",
      "author": "butler",
      "summary": "H4: 从引文章节链接推导sources字段",
      "parent_rev": "20260425-140703-699390",
      "content_hash": "sha256:d48f0b5b8982ca545e7f2dfe467e01f3997f281ba43c5e0b9f234d80ebbb5872",
      "size": 1971,
      "content": "---\nid: 左庶长\ntype: official\nlabel: 左庶长\naliases: []\ncanonical_name: 左庶长\ntags: [\"官职\", \"爵位\"]\nfeatured: false\ndescription: \"《史记》中的官职（爵位），出现于《史记》7处\"\nsources: [秦本纪, 平准书, 商君列传, 白起王翦列传]\n---\n# 左庶长\n\n出现于《史记》**7** 处。\n\n## 史记引文\n\n《史记》中出现 **7** 处。\n\n**章节分布：**\n\n- [[005_秦本纪|秦本纪]]：（005-51）\n- [[030_平准书|平准书]]：（030-24）、（030-46）\n- [[068_商君列传|商君列传]]：（068-3）\n- [[073_白起王翦列传|白起王翦列传]]：（073-1）、（073-4）\n- [[111_卫将军骠骑列传|卫将军骠骑列传]]：（111-50）\n\n**引文摘录（共 7 处，下列仅示 5 条）：**\n\n> 出自 [[005_秦本纪|秦本纪]] （005-51）：…公善之。甘龙、杜挚等弗然，相与争之。卒用卫鞅法，百姓苦之；居三年，百姓便之。乃拜卫鞅为**左庶长**。其事在商君语中。\n>\n> 出自 [[030_平准书|平准书]] （030-24）：天子乃思卜式之言，召拜卜式为中郎，爵**左庶长**，赐田十顷，布告天下，使明知之。 ## 卜式传记\n>\n> 出自 [[030_平准书|平准书]] （030-46）：…。时长之中，太仓、甘泉仓满。边馀穀诸物均输帛五百万匹。民不益赋而天下用饶。於是弘羊赐爵**左庶长**，黄金再百斤焉。 ## 卜式与桑弘羊的矛盾\n>\n> 出自 [[068_商君列传|商君列传]] （068-3）：…古而王，夏殷不易礼而亡。反古者不可非，而循礼者不足多。” 秦孝公曰：“善。” 以商鞅为**左庶长**，卒定变法之令。\n>\n> 出自 [[073_白起王翦列传|白起王翦列传]] （073-1）：白起者，郿人也。善用兵，事秦昭王。秦昭王十三年，而白起为**左庶长**，将而击韩之新城。是岁，魏冉相秦，举任鄙以为汉中守。其明年，白起为左更，攻韩、魏於伊阙…\n\n## 相关页面\n\n"
    },
    {
      "rev_id": "20260425-140703-699390",
      "timestamp": "2026-04-25T14:07:03Z",
      "author": "butler",
      "summary": "H4: 补全实体词条description字段",
      "parent_rev": null,
      "content_hash": "sha256:699390cdda58a8d4a40b65c2b35235e82979e149dcf4cc25737137957fa07a2e",
      "size": 1905,
      "content": "---\nid: 左庶长\ntype: official\nlabel: 左庶长\naliases: []\ncanonical_name: 左庶长\ntags: [\"官职\", \"爵位\"]\nfeatured: false\ndescription: \"《史记》中的官职（爵位），出现于《史记》7处\"\n---\n# 左庶长\n\n出现于《史记》**7** 处。\n\n## 史记引文\n\n《史记》中出现 **7** 处。\n\n**章节分布：**\n\n- [[005_秦本纪|秦本纪]]：（005-51）\n- [[030_平准书|平准书]]：（030-24）、（030-46）\n- [[068_商君列传|商君列传]]：（068-3）\n- [[073_白起王翦列传|白起王翦列传]]：（073-1）、（073-4）\n- [[111_卫将军骠骑列传|卫将军骠骑列传]]：（111-50）\n\n**引文摘录（共 7 处，下列仅示 5 条）：**\n\n> 出自 [[005_秦本纪|秦本纪]] （005-51）：…公善之。甘龙、杜挚等弗然，相与争之。卒用卫鞅法，百姓苦之；居三年，百姓便之。乃拜卫鞅为**左庶长**。其事在商君语中。\n>\n> 出自 [[030_平准书|平准书]] （030-24）：天子乃思卜式之言，召拜卜式为中郎，爵**左庶长**，赐田十顷，布告天下，使明知之。 ## 卜式传记\n>\n> 出自 [[030_平准书|平准书]] （030-46）：…。时长之中，太仓、甘泉仓满。边馀穀诸物均输帛五百万匹。民不益赋而天下用饶。於是弘羊赐爵**左庶长**，黄金再百斤焉。 ## 卜式与桑弘羊的矛盾\n>\n> 出自 [[068_商君列传|商君列传]] （068-3）：…古而王，夏殷不易礼而亡。反古者不可非，而循礼者不足多。” 秦孝公曰：“善。” 以商鞅为**左庶长**，卒定变法之令。\n>\n> 出自 [[073_白起王翦列传|白起王翦列传]] （073-1）：白起者，郿人也。善用兵，事秦昭王。秦昭王十三年，而白起为**左庶长**，将而击韩之新城。是岁，魏冉相秦，举任鄙以为汉中守。其明年，白起为左更，攻韩、魏於伊阙…\n\n## 相关页面\n\n"
    }
  ]
}
