{
  "page": "жҳҘз”і",
  "latest_rev_id": "20260424-070920-739727",
  "revision_count": 1,
  "revisions": [
    {
      "rev_id": "20260424-070920-739727",
      "timestamp": "2026-04-24T07:09:20Z",
      "author": "butler",
      "summary": "butler/create: жҳҘз”іпјҲredirectвҶ’жҳҘз”іеҗӣпјү",
      "parent_rev": null,
      "content_hash": "sha256:7397274c5dca2d2a35553e21aa7077c56a814e8c83532cbce2817d265801f411",
      "size": 142,
      "content": "---\nid: жҳҘз”і\ntype: redirect\nlabel: жҳҘз”і\naliases: [жҳҘз”і]\ncanonical_name: жҳҘз”іеҗӣ\ntags: []\nfeatured: false\n---\n\n#REDIRECT [[жҳҘз”іеҗӣ]]\n",
      "size_before": 0
    }
  ]
}
