{
  "page": "昭襄王卒孝文王立",
  "latest_rev_id": "20260423-155221-3d1897",
  "revision_count": 1,
  "revisions": [
    {
      "rev_id": "20260423-155221-3d1897",
      "timestamp": "2026-04-23T15:52:21Z",
      "author": "butler",
      "summary": "butler/import-event: 昭襄王卒孝文王立 新建 (005-143)",
      "parent_rev": null,
      "content_hash": "sha256:3d18976ee016c422486d0c7f8d230fc07533a9350c7d90d54f94ec1508bfe2d5",
      "size": 1128,
      "content": "---\nid: \"昭襄王卒孝文王立\"\ntype: event\ntitle: 昭襄王卒孝文王立\ndescription: 昭襄王五十六年秋去世，子孝文王继位。尊唐八子为唐太后，与先王合葬。韩王衰绖入吊，诸侯皆遣将相来吊。昭襄王在位五十六年，是秦统一天下最关键的奠基者。\ntags: [史记, 事件, 秦本纪]\nsources: [秦本纪]\nevent_ids: [005-143]\ndate: \"〖%五十六年〗〖%秋〗 （公元前251年）\"\n---\n\n# 昭襄王卒孝文王立\n\n> 昭襄王五十六年秋去世，子孝文王继位。尊唐八子为唐太后，与先王合葬。韩王衰绖入吊，诸侯皆遣将相来吊。昭襄王在位五十六年，是秦统一天下最关键的奠基者。\n\n**主要人物**：唐八子（唐太后）、孝文王、昭襄王\n\n## 事件经过\n\n昭襄王五十六年秋去世，子孝文王继位。尊唐八子为唐太后，与先王合葬。韩王衰绖入吊，诸侯皆遣将相来吊。昭襄王在位五十六年，是秦统一天下最关键的奠基者。\n\n## 原文\n\n> 五十六年秋，昭襄王卒，子孝文王立。尊唐八子为唐太后，而合其葬於先王。\n\n"
    }
  ]
}
