{
  "page": "武下",
  "latest_rev_id": "20260424-070337-8f3102",
  "revision_count": 1,
  "revisions": [
    {
      "rev_id": "20260424-070337-8f3102",
      "timestamp": "2026-04-24T07:03:37Z",
      "author": "butler",
      "summary": "butler/import-places: 新建地名页",
      "parent_rev": null,
      "content_hash": "sha256:8f3102488493eaa8fa397f761228fd7d93b5bef673e8c7d984d04ab2882de204",
      "size": 406,
      "content": "---\nid: 武下\ntype: place\nlabel: 武下\naliases: []\ntags: [\"地名\", \"城邑\"]\nauto_generated: true\n---\n\n# 武下\n\n## 史记引文\n\n《史记》中出现 **1** 次，见于以下章节：\n\n[[044_魏世家]]\n\n**引文摘录：**\n\n出自 [[044_魏世家]]（21）：\n> 陵。三十六年，秦侵我阴晋。 三十八年，伐秦，败我武下，得其将识。是岁，文侯|魏武侯立，是为武侯\n"
    }
  ]
}
