{
  "page": "毌丘",
  "latest_rev_id": "20260424-070339-1b01c0",
  "revision_count": 1,
  "revisions": [
    {
      "rev_id": "20260424-070339-1b01c0",
      "timestamp": "2026-04-24T07:03:39Z",
      "author": "butler",
      "summary": "butler/import-places: 新建地名页",
      "parent_rev": null,
      "content_hash": "sha256:1b01c0bc32c69cb9c98e3c7b858aad12c4ba8e6b96c1d3bb2d740b5e453e0e7f",
      "size": 376,
      "content": "---\nid: 毌丘\ntype: place\nlabel: 毌丘\naliases: []\ntags: [\"地名\", \"城邑\"]\nauto_generated: true\n---\n\n# 毌丘\n\n## 史记引文\n\n《史记》中出现 **1** 次，见于以下章节：\n\n[[046_田敬仲完世家]]\n\n**引文摘录：**\n\n出自 [[046_田敬仲完世家]]：\n> 和立。田太公相齐宣公。宣公|齐宣公与郑人会西城。伐卫，取毌丘。宣公\n"
    }
  ]
}
