{
  "page": "燕国除为郡",
  "latest_rev_id": "20260425-122204-3a2ec8",
  "revision_count": 6,
  "revisions": [
    {
      "rev_id": "20260425-122204-3a2ec8",
      "timestamp": "2026-04-25T12:22:04Z",
      "author": "butler",
      "summary": "H4: pn=(051-016)（from event_ids）",
      "parent_rev": "20260425-091448-26d884",
      "content_hash": "sha256:3a2ec86312e7ae72110c5c22fba42378d746b0664660b6fcaa823bf567439e88",
      "size": 795,
      "content": "---\nid: \"燕国除为郡\"\ntype: event\ntitle: 燕国除为郡\ndescription: 诏下公卿，皆议定国禽兽行、乱人伦、逆天，当诛。定国自杀，国除为郡。\ntags: [史记, 事件, 荆燕世家]\nsources: [荆燕世家]\nevent_ids: [051-016]\npn: (051-016)\ndate: \"元朔二年 （公元前127年）\"\n---\n\n::: meta\npn: (051-10)\nevent_type: 政治整顿\nchapter: [荆燕世家]\n:::\n\n# 燕国除为郡\n\n> 诏下公卿，皆议定国禽兽行、乱人伦、逆天，当诛。定国自杀，国除为郡。\n\n**主要人物**：定国\n\n## 事件经过\n\n诏下公卿，皆议定国禽兽行、乱人伦、逆天，当诛。定国自杀，国除为郡。\n\n## 原文\n\n> 诏下公卿，皆议曰：'定国禽兽行，乱人伦，逆天，当诛。'上许之。定国自杀，国除为郡。\n\n"
    },
    {
      "rev_id": "20260425-091448-26d884",
      "timestamp": "2026-04-25T09:14:48Z",
      "author": "butler",
      "summary": "butler/H15: 清理date字段标注符号",
      "parent_rev": "20260423-164837-1563f5",
      "content_hash": "sha256:26d884175b1cdafdc72a748f70ee8b2793dc784057eb3e42a68d484320f836a7",
      "size": 781,
      "content": "---\nid: \"燕国除为郡\"\ntype: event\ntitle: 燕国除为郡\ndescription: 诏下公卿，皆议定国禽兽行、乱人伦、逆天，当诛。定国自杀，国除为郡。\ntags: [史记, 事件, 荆燕世家]\nsources: [荆燕世家]\nevent_ids: [051-016]\ndate: \"元朔二年 （公元前127年）\"\n---\n\n::: meta\npn: (051-10)\nevent_type: 政治整顿\nchapter: [荆燕世家]\n:::\n\n# 燕国除为郡\n\n> 诏下公卿，皆议定国禽兽行、乱人伦、逆天，当诛。定国自杀，国除为郡。\n\n**主要人物**：定国\n\n## 事件经过\n\n诏下公卿，皆议定国禽兽行、乱人伦、逆天，当诛。定国自杀，国除为郡。\n\n## 原文\n\n> 诏下公卿，皆议曰：'定国禽兽行，乱人伦，逆天，当诛。'上许之。定国自杀，国除为郡。\n\n"
    },
    {
      "rev_id": "20260423-164837-1563f5",
      "timestamp": "2026-04-23T16:48:37Z",
      "author": "butler",
      "summary": "butler/fix-pn: 修正PN格式 + 添加章节关联",
      "parent_rev": "20260423-162902-ddad32",
      "content_hash": "sha256:1563f571a861f38b57aafa9d61ad241e913424cba607fb002bb94a75f32b4834",
      "size": 788,
      "content": "---\nid: \"燕国除为郡\"\ntype: event\ntitle: 燕国除为郡\ndescription: 诏下公卿，皆议定国禽兽行、乱人伦、逆天，当诛。定国自杀，国除为郡。\ntags: [史记, 事件, 荆燕世家]\nsources: [荆燕世家]\nevent_ids: [051-016]\ndate: \"〖%元朔二年〗 （公元前127年）\"\n---\n\n::: meta\npn: (051-10)\nevent_type: 政治整顿\nchapter: [荆燕世家]\n:::\n\n# 燕国除为郡\n\n> 诏下公卿，皆议定国禽兽行、乱人伦、逆天，当诛。定国自杀，国除为郡。\n\n**主要人物**：定国\n\n## 事件经过\n\n诏下公卿，皆议定国禽兽行、乱人伦、逆天，当诛。定国自杀，国除为郡。\n\n## 原文\n\n> 诏下公卿，皆议曰：'定国禽兽行，乱人伦，逆天，当诛。'上许之。定国自杀，国除为郡。\n\n"
    },
    {
      "rev_id": "20260423-162902-ddad32",
      "timestamp": "2026-04-23T16:29:02Z",
      "author": "butler",
      "summary": "butler/add-pn: 补全:::meta段落位置+事件元数据",
      "parent_rev": "20260423-161156-211fa8",
      "content_hash": "sha256:ddad32963180a7141b36d1fe5cd7c46e24a05a16fd119ee02f63e76b7049f780",
      "size": 762,
      "content": "---\nid: \"燕国除为郡\"\ntype: event\ntitle: 燕国除为郡\ndescription: 诏下公卿，皆议定国禽兽行、乱人伦、逆天，当诛。定国自杀，国除为郡。\ntags: [史记, 事件, 荆燕世家]\nsources: [荆燕世家]\nevent_ids: [051-016]\ndate: \"〖%元朔二年〗 （公元前127年）\"\n---\n\n::: meta\npn: \"[10]\"\nevent_type: 政治整顿\n:::\n\n# 燕国除为郡\n\n> 诏下公卿，皆议定国禽兽行、乱人伦、逆天，当诛。定国自杀，国除为郡。\n\n**主要人物**：定国\n\n## 事件经过\n\n诏下公卿，皆议定国禽兽行、乱人伦、逆天，当诛。定国自杀，国除为郡。\n\n## 原文\n\n> 诏下公卿，皆议曰：'定国禽兽行，乱人伦，逆天，当诛。'上许之。定国自杀，国除为郡。\n\n"
    },
    {
      "rev_id": "20260423-161156-211fa8",
      "timestamp": "2026-04-23T16:11:56Z",
      "author": "butler",
      "summary": "butler/add-pn: 补全PN+元数据 (paragraph_refs, event_type)",
      "parent_rev": "20260423-155338-4b3f13",
      "content_hash": "sha256:211fa806dabcf8e664febdf8714e2c87c906106ac6cfb0273ea09502355b5cc3",
      "size": 771,
      "content": "paragraph_refs:\n  051-016: \"[10]\"\nevent_type: 政治整顿\n---\nid: \"燕国除为郡\"\ntype: event\ntitle: 燕国除为郡\ndescription: 诏下公卿，皆议定国禽兽行、乱人伦、逆天，当诛。定国自杀，国除为郡。\ntags: [史记, 事件, 荆燕世家]\nsources: [荆燕世家]\nevent_ids: [051-016]\ndate: \"〖%元朔二年〗 （公元前127年）\"\n---\n\n# 燕国除为郡\n\n> 诏下公卿，皆议定国禽兽行、乱人伦、逆天，当诛。定国自杀，国除为郡。\n\n**主要人物**：定国\n\n## 事件经过\n\n诏下公卿，皆议定国禽兽行、乱人伦、逆天，当诛。定国自杀，国除为郡。\n\n## 原文\n\n> 诏下公卿，皆议曰：'定国禽兽行，乱人伦，逆天，当诛。'上许之。定国自杀，国除为郡。\n\n"
    },
    {
      "rev_id": "20260423-155338-4b3f13",
      "timestamp": "2026-04-23T15:53:38Z",
      "author": "butler",
      "summary": "butler/import-event: 燕国除为郡 新建 (051-016)",
      "parent_rev": null,
      "content_hash": "sha256:4b3f1386cad8f3edc9af592ed2b4c32da950ca98aec564c43d58fcb12fbb5dd7",
      "size": 712,
      "content": "---\nid: \"燕国除为郡\"\ntype: event\ntitle: 燕国除为郡\ndescription: 诏下公卿，皆议定国禽兽行、乱人伦、逆天，当诛。定国自杀，国除为郡。\ntags: [史记, 事件, 荆燕世家]\nsources: [荆燕世家]\nevent_ids: [051-016]\ndate: \"〖%元朔二年〗 （公元前127年）\"\n---\n\n# 燕国除为郡\n\n> 诏下公卿，皆议定国禽兽行、乱人伦、逆天，当诛。定国自杀，国除为郡。\n\n**主要人物**：定国\n\n## 事件经过\n\n诏下公卿，皆议定国禽兽行、乱人伦、逆天，当诛。定国自杀，国除为郡。\n\n## 原文\n\n> 诏下公卿，皆议曰：'定国禽兽行，乱人伦，逆天，当诛。'上许之。定国自杀，国除为郡。\n\n"
    }
  ]
}
