{
  "page": "荆轲",
  "latest_rev_id": "20260426-092156-878f16",
  "revision_count": 13,
  "revisions": [
    {
      "rev_id": "20260426-092156-878f16",
      "timestamp": "2026-04-26T09:21:56Z",
      "author": "butler",
      "summary": "sanjia-entity: 追加三家注 15 条",
      "parent_rev": "20260426-001030-dae317",
      "content_hash": "sha256:878f1666c8387b5caa1a432e6a0a2ec539d21794df0355b8342e3c6bbf581cb1",
      "size_before": 7390,
      "size": 11875,
      "content": "---\nid: 荆轲\ntype: person\nlabel: 荆轲\npn: (086-014)\nsources: [刺客列传, 秦始皇本纪, 六国年表]\ndescription: \"荆轲（？— 前 227），卫人，游历至燕，燕人称'荆卿'； 性沈深好书，嗜酒，与高渐离为友； 燕太子丹礼待，受命刺秦王—— 以樊於期首级和燕督亢地图为信物， 图穷匕见，未能刺中，身被八创，倚柱而笑，骂…\"\naliases: [荆轲, 荆卿, 庆卿]\ncanonical_name: 荆轲\nxing: 荆\nming: 轲\nbirth_ce: -?\ndeath_ce: -227\ntags: [战国, 燕国, 刺客, 图穷匕见, 易水送别, 列传人物]\nquality: featured\n---\n# 荆轲\n\n[[荆轲]]（？— 前 227），卫人，游历至燕，燕人称\"荆卿\"；\n性沈深好书，嗜酒，与高渐离为友；\n燕太子丹礼待，受命刺秦王——\n以**樊於期首级**和**燕督亢地图**为信物，\n图穷匕见，未能刺中，身被八创，倚柱而笑，骂曰欲生劫之以得约契报太子；\n左右杀轲，刺秦失败。\n\n《史记》主要记载见[[086_刺客列传|086 刺客列传]]。\n\n---\n\n## 生平\n\n### 易水送别 · 风萧萧兮\n\n太子丹患秦进逼，荆轲请得樊於期首级与燕督亢地图——\n\n> 太子及宾客知其事者，皆白衣冠以送之。至易水之上，既祖，取道，高渐离击筑，荆轲和而歌，为变徵之声，士皆垂泪涕泣。又前而为歌曰：\"风萧萧兮易水寒，壮士一去兮不复还！\"复为羽声慷慨，士皆瞋目，发尽上指冠。於是荆轲就车而去，终已不顾。（[[086_刺客列传|086-033]]）\n\n### 图穷匕见 · 倚柱而笑\n\n至秦，以地图献秦王——\n\n> 荆轲奉樊於期头函，而秦舞阳奉地图柙，以次进。至陛，秦舞阳色变振恐，群臣怪之。荆轲顾笑舞阳，前谢曰：\"北蕃蛮夷之鄙人，未尝见天子，故振慴。原大王少假借之，使得毕使於前。\"秦王谓轲曰：\"取舞阳所持地图。\"轲既取图奏之，秦王发图，图穷而匕首见。因左手把秦王之袖，而右手持匕首揕之。未至身，秦王惊，自引而起，袖绝。（[[086_刺客列传|086-034]]）\n\n秦王环柱而走，群臣惶急失度，侍医[[夏无且]]以药囊投荆轲——秦王负剑拔之，断荆轲左股。\n\n> 轲自知事不就，倚柱而笑，箕踞以骂曰：\"事所以不成者，以欲生劫之，必得约契以报太子也。\"於是左右既前杀轲，秦王不怡者良久。（[[086_刺客列传|086-034]]）\n\n---\n\n## \"倚柱而笑\"——失败的自我诠释\n\n刺秦失败的最后一刻，荆轲倚柱而笑：\n\n> 轲自知事不就，倚柱而笑，箕踞以骂曰：\n> \"**事所以不成者，以欲生劫之，必得约契以报太子也。**\"\n> 於是左右既前杀轲，秦王不怡者良久。（[[086_刺客列传|086-034]]）\n\n这是荆轲留下的最后解释——也是《史记》中最复杂的\"失败\"时刻之一。\n\n他没有说\"我技不如人\"，也没有说\"这是天命\"——\n他说的是**一个战略选择导致的失败**：\n他想的是生擒秦王、逼签条约（\"欲生劫之，得约契以报太子\"），\n所以在能杀而未杀的瞬间，他选择了更难的路。\n这个选择，导致了刺杀失败。\n\n**\"倚柱而笑\"**——这一肢体语言是整个场景的核心：\n在自知将死的瞬间，笑着解释失败的原因，\n是荆轲对自身抉择的最后辩护，也是对任何外人猜疑的最后拒绝。\n\n太史公在传末为荆轲等五位刺客辩护：\n\n> 此其义或成或不成，然**其立意较然，不欺其志，名垂後世，岂妄也哉**！（[[086_刺客列传|086-038]]）\n\n\"不欺其志\"——荆轲没有欺骗自己的动机（他知道这是必死之行），\n也没有欺骗太子丹（他在行动时已知秦舞阳临阵失色，仍坚持向前）。\n成败是历史的结果，\"立意较然\"才是太史公的评价标准。\n\n太史公将荆轲与[[曹沫]]、[[豫让]]、[[聂政]]、[[专诸]]并列五人——\n他关注的不是刺杀是否成功，而是这些人的\"志\"：\n一种在明知失败概率极高时，仍选择践行诺言的精神结构。\n这是《史记》中对\"义\"最边缘、也最纯粹的展示。\n\n## 太史公曰\n\n> 太史公曰：自曹沫至荆轲五人，此其义或成或不成，然其立意较然，不欺其志，名垂後世，岂妄也哉！（[[086_刺客列传|086-038]]）\n\n---\n\n## 对照表\n\n| 项目 | 内容 |\n| --- | --- |\n| 生年 | 不详（约前 312—前 243 年[^life]） |\n| 籍贯 | 卫（先祖为齐人，徙卫） |\n| 卒年 | 前 227 年（刺秦失败，被杀于咸阳宫） |\n| 关键事迹 | 易水送别、图穷匕见、倚柱骂曰 |\n| 主要传记 | [[086_刺客列传|086 刺客列传]] |\n\n---\n\n## 典故与成语\n\n- **图穷匕见** — 地图展开尽头，匕首显现；比喻阴谋败露\n- **风萧萧兮易水寒** — 千古悲歌，壮士诀别之词\n- **荆轲刺秦** — 中国历史上最著名的刺杀行动\n\n---\n\n## 相关章节\n\n- [[086_刺客列传|086 刺客列传]]（主要出处，含曹沫、专诸、豫让、聂政、荆轲）\n\n## 相关人物\n\n- [[高渐离]]（挚友，击筑送行，后以筑击秦始皇）\n- [[太子丹]]（主君，礼遇荆轲，供太牢车骑美女以顺其意）\n- [[樊於期]]（自刭献首，成全荆轲计划）\n- [[夏无且]]（刺秦时以药囊击荆轲）\n\n---\n\n[^life]: 生年推断参见[《荆轲生卒年推断》](../../doc/lifespan_inference/战国/燕荆轲.md)（置信度：低，约前312—前243年生）。\n\n## 生平大事 (自 kg 事件索引)\n\n- 约公元前228年 · 田光荐荆轲自刎  [`086-014`]\n- 约公元前228年 · 樊於期献首  [`086-015`]\n- （公元前227年） · 易水送别（易水）  [`086-016`]\n- （公元前227年） · 荆轲刺秦王（咸阳宫）  [`086-017`]\n\n## 史记引文\n\n《史记》中出现 **77** 处（标注符号：〖@荆轲〗）。\n\n**章节分布：**\n\n- [[006_秦始皇本纪|秦始皇本纪]]：§27.1、§27.2、§34.4\n- [[015_六国年表|六国年表]]：§r250\n- [[034_燕召公世家|燕召公世家]]：§22.1\n- [[044_魏世家|魏世家]]：§73\n- [[046_田敬仲完世家|田敬仲完世家]]：§26.2\n- [[073_白起王翦列传|白起王翦列传]]：§9\n- [[083_鲁仲连邹阳列传|鲁仲连邹阳列传]]：§16、§18、§21、§23\n- [[086_刺客列传|刺客列传]]：§24、§25、§26、§27、§28、§29、§36、§37 等共 23 处\n- [[088_蒙恬列传|蒙恬列传]]：§7\n- [[110_匈奴列传|匈奴列传]]：§16\n\n**引文摘录（共 77 处，下列仅示 5 条）：**\n\n> 出自 [[006_秦始皇本纪|秦始皇本纪]] §27.1：二十年，燕太子丹患秦兵至国，恐，使**荆轲**刺秦王。\n>\n> 出自 [[006_秦始皇本纪|秦始皇本纪]] §27.2：秦王觉之，体解**荆轲**以徇，而使王翦、辛胜攻燕。\n>\n> 出自 [[015_六国年表|六国年表]] §r250：|  [r250]  |    |  二十。太子丹使**荆轲**刺王，觉之。王翦将击燕。  |  魏王魏假元年  |    |  代王赵嘉元年  |  …\n>\n> 出自 [[034_燕召公世家|燕召公世家]] §22.1：燕见秦且灭六国，秦兵临易水，祸且至燕。太子燕太子丹阴养壮士二十人，使**荆轲**献督亢地图於秦，因袭刺秦王。秦王觉，杀荆轲，使将军王翦击燕。二十九年，秦攻拔我蓟，燕王亡…\n>\n> 出自 [[044_魏世家|魏世家]] §73：王假元年，燕太子燕太子丹使**荆轲**刺秦王，秦王觉之。\n\n## 三家注\n\n以下是《史记》三家注中直接注释「荆轲」相关文字的条目。\n\n#### 出自 [[086_刺客列传]]\n\n##### n067 · 「……荆卿好读书击剑，**荆卿好读书击剑，**以术说衞元君，衞元君不用。其后秦伐魏，置……」\n\n> **【集解】** 吕氏剑技曰：「持短入长，倏忽从横。」\n\n##### n069 · 「……荆轲尝游过榆次，**荆轲尝游过榆次，**与盖聂论剑，……」\n\n> **【正义】** 并州县也。\n\n##### n072 · 「……于邯郸，鲁句践与荆轲博，争道，**荆轲游于邯郸，鲁句践与荆轲博，争道，**鲁句践怒而叱之，荆轲嘿而逃去，遂不复会。……」\n\n> **【索隐】** 鲁，姓；句践，名也。与越王同，或有意义。俗本「践」作「贱」，非。\n\n##### n073 · 「……，爱燕之狗屠及善击筑者高渐离。**荆轲既至燕，爱燕之狗屠及善击筑者高渐离。**荆轲嗜酒，日与狗屠及高渐离饮于燕市，酒酣……」\n\n> **【索隐】** 筑似琴，有弦，用竹击之，取以为名。渐音如字，王义（之）音哉廉反。\n\n##### n074 · 「……旁若无人者。荆轲虽游于酒人乎，**已而相泣，旁若无人者。荆轲虽游于酒人乎，**然其为人沈深好书；其所游诸侯，尽与其贤豪……」\n\n> **【集解】** 徐广曰：「饮酒之人。」\n\n##### n088 · 「……骑美女恣荆轲所欲，以顺适其意。**物闲进，车骑美女恣荆轲所欲，以顺适其意。**……」\n\n> **【索隐】** 燕丹子曰「轲与太子游东宫池，轲拾瓦投鼃，太子捧金丸进之。又共乘千里马，轲曰『千里马肝美』，即杀马进肝。太子与樊将军置酒于华阳台，出美人能鼓琴，轲曰『好手也』，断以玉盘盛之。轲曰『太子遇轲甚厚』」是也。\n\n##### n090 · 「……臣，臣左手把其袖，右手揕其匈，**王必喜而见臣，臣左手把其袖，右手揕其匈，**然则将军之仇报而燕见陵之愧除矣。将军岂有……」\n\n> **【集解】** 徐广曰：「揕音张鸩切。一作『抗』。」\n>\n> **【索隐】** 徐氏音丁鸩反。揕谓以剑刺其胸也。又云一作「抗」。抗音苦浪反，言抗拒也，其义非。\n\n##### n097 · 「……送之。至易水之上，既祖，取道，**皆白衣冠以送之。至易水之上，既祖，取道，**高渐离击筑，荆轲和而歌，为变徵之声，……」\n\n> **【正义】** 易州在幽州归义县界。\n\n##### n102 · 「……起，袖绝。拔剑，剑长，操其室。**惊，自引而起，袖绝。拔剑，剑长，操其室。**时惶急，剑坚，故不可立拔。荆轲逐秦王，秦……」\n\n> **【索隐】** 室谓鞘也。\n>\n> **【正义】** 燕丹子云：「左手揕其胸。秦王曰：『今日之事，从子计耳。乞听瑟而死。』召姬人鼓琴，琴声曰『罗縠单衣，可裂而绝；八尺屏风，可超而越；鹿卢之剑，可负而拔』。王于是奋袖超屏风走之。」\n\n##### n103 · 「……侍殿上者不得持尺寸之兵；诸郎中**秦法，群臣侍殿上者不得持尺寸之兵；诸郎中**执兵皆陈殿下，非有诏召不得上。方急时，不……」\n\n> **【索隐】** 若今宿衞之官。\n\n##### n105 · 「……医夏无且以其所奉药囊提荆轲也。**以其所奉药囊提荆轲也。**秦王方环柱走，卒惶急，不知所为，左右乃曰……」\n\n> **【正义】** 提，姪帝反。\n\n##### n107 · 「……。荆轲废，乃引其匕首以擿秦王，**，断其左股。荆轲废，乃引其匕首以擿秦王，**不中，中桐柱。……」\n\n> **【索隐】** 擿与「掷」同，古字耳，音持益反。\n\n##### n108 · 「……其匕首以擿秦王，不中，中桐柱。**不中，中桐柱。**秦王复击轲，轲被八创。轲自知事不就，倚柱……」\n\n> **【正义】** 燕丹子云：「荆轲拔匕首掷秦王，决耳入铜柱，火出。」\n\n##### n120 · 「……嗟乎，惜哉其不讲于刺剑之术也！**，私曰：「嗟乎，惜哉其不讲于刺剑之术也！**甚矣吾不知人也！曩者吾叱之，彼乃以我为非……」\n\n> **【索隐】** 案：不讲谓不论习之。\n\n##### n122 · 「……其义或成或不成，然其立意较然，**轲五人，此其义或成或不成，然其立意较然，**不欺其志，名垂后世，岂妄也哉！……」\n\n> **【索隐】** 较，明也。\n\n"
    },
    {
      "rev_id": "20260426-001030-dae317",
      "timestamp": "2026-04-26T00:10:30Z",
      "author": "butler",
      "summary": "premium-upgrade: 倚柱而笑——失败的自我诠释分析",
      "parent_rev": "20260425-133013-cca258",
      "content_hash": "sha256:dae31738ffe8f6f90899f6d4d7f5b1dabfa3d43b548c01775ae454f7bed03a3e",
      "size_before": 5691,
      "size": 7390,
      "content": "---\nid: 荆轲\ntype: person\nlabel: 荆轲\npn: (086-014)\nsources: [刺客列传, 秦始皇本纪, 六国年表]\ndescription: \"荆轲（？— 前 227），卫人，游历至燕，燕人称'荆卿'； 性沈深好书，嗜酒，与高渐离为友； 燕太子丹礼待，受命刺秦王—— 以樊於期首级和燕督亢地图为信物， 图穷匕见，未能刺中，身被八创，倚柱而笑，骂…\"\naliases: [荆轲, 荆卿, 庆卿]\ncanonical_name: 荆轲\nbirth_ce: -?\ndeath_ce: -227\ntags: [战国, 燕国, 刺客, 图穷匕见, 易水送别, 列传人物]\nquality: featured\n---\n# 荆轲\n\n[[荆轲]]（？— 前 227），卫人，游历至燕，燕人称\"荆卿\"；\n性沈深好书，嗜酒，与高渐离为友；\n燕太子丹礼待，受命刺秦王——\n以**樊於期首级**和**燕督亢地图**为信物，\n图穷匕见，未能刺中，身被八创，倚柱而笑，骂曰欲生劫之以得约契报太子；\n左右杀轲，刺秦失败。\n\n《史记》主要记载见[[086_刺客列传|086 刺客列传]]。\n\n---\n\n## 生平\n\n### 易水送别 · 风萧萧兮\n\n太子丹患秦进逼，荆轲请得樊於期首级与燕督亢地图——\n\n> 太子及宾客知其事者，皆白衣冠以送之。至易水之上，既祖，取道，高渐离击筑，荆轲和而歌，为变徵之声，士皆垂泪涕泣。又前而为歌曰：\"风萧萧兮易水寒，壮士一去兮不复还！\"复为羽声慷慨，士皆瞋目，发尽上指冠。於是荆轲就车而去，终已不顾。（[[086_刺客列传|086-033]]）\n\n### 图穷匕见 · 倚柱而笑\n\n至秦，以地图献秦王——\n\n> 荆轲奉樊於期头函，而秦舞阳奉地图柙，以次进。至陛，秦舞阳色变振恐，群臣怪之。荆轲顾笑舞阳，前谢曰：\"北蕃蛮夷之鄙人，未尝见天子，故振慴。原大王少假借之，使得毕使於前。\"秦王谓轲曰：\"取舞阳所持地图。\"轲既取图奏之，秦王发图，图穷而匕首见。因左手把秦王之袖，而右手持匕首揕之。未至身，秦王惊，自引而起，袖绝。（[[086_刺客列传|086-034]]）\n\n秦王环柱而走，群臣惶急失度，侍医[[夏无且]]以药囊投荆轲——秦王负剑拔之，断荆轲左股。\n\n> 轲自知事不就，倚柱而笑，箕踞以骂曰：\"事所以不成者，以欲生劫之，必得约契以报太子也。\"於是左右既前杀轲，秦王不怡者良久。（[[086_刺客列传|086-034]]）\n\n---\n\n## \"倚柱而笑\"——失败的自我诠释\n\n刺秦失败的最后一刻，荆轲倚柱而笑：\n\n> 轲自知事不就，倚柱而笑，箕踞以骂曰：\n> \"**事所以不成者，以欲生劫之，必得约契以报太子也。**\"\n> 於是左右既前杀轲，秦王不怡者良久。（[[086_刺客列传|086-034]]）\n\n这是荆轲留下的最后解释——也是《史记》中最复杂的\"失败\"时刻之一。\n\n他没有说\"我技不如人\"，也没有说\"这是天命\"——\n他说的是**一个战略选择导致的失败**：\n他想的是生擒秦王、逼签条约（\"欲生劫之，得约契以报太子\"），\n所以在能杀而未杀的瞬间，他选择了更难的路。\n这个选择，导致了刺杀失败。\n\n**\"倚柱而笑\"**——这一肢体语言是整个场景的核心：\n在自知将死的瞬间，笑着解释失败的原因，\n是荆轲对自身抉择的最后辩护，也是对任何外人猜疑的最后拒绝。\n\n太史公在传末为荆轲等五位刺客辩护：\n\n> 此其义或成或不成，然**其立意较然，不欺其志，名垂後世，岂妄也哉**！（[[086_刺客列传|086-038]]）\n\n\"不欺其志\"——荆轲没有欺骗自己的动机（他知道这是必死之行），\n也没有欺骗太子丹（他在行动时已知秦舞阳临阵失色，仍坚持向前）。\n成败是历史的结果，\"立意较然\"才是太史公的评价标准。\n\n太史公将荆轲与[[曹沫]]、[[豫让]]、[[聂政]]、[[专诸]]并列五人——\n他关注的不是刺杀是否成功，而是这些人的\"志\"：\n一种在明知失败概率极高时，仍选择践行诺言的精神结构。\n这是《史记》中对\"义\"最边缘、也最纯粹的展示。\n\n## 太史公曰\n\n> 太史公曰：自曹沫至荆轲五人，此其义或成或不成，然其立意较然，不欺其志，名垂後世，岂妄也哉！（[[086_刺客列传|086-038]]）\n\n---\n\n## 对照表\n\n| 项目 | 内容 |\n| --- | --- |\n| 生年 | 不详（约前 312—前 243 年[^life]） |\n| 籍贯 | 卫（先祖为齐人，徙卫） |\n| 卒年 | 前 227 年（刺秦失败，被杀于咸阳宫） |\n| 关键事迹 | 易水送别、图穷匕见、倚柱骂曰 |\n| 主要传记 | [[086_刺客列传|086 刺客列传]] |\n\n---\n\n## 典故与成语\n\n- **图穷匕见** — 地图展开尽头，匕首显现；比喻阴谋败露\n- **风萧萧兮易水寒** — 千古悲歌，壮士诀别之词\n- **荆轲刺秦** — 中国历史上最著名的刺杀行动\n\n---\n\n## 相关章节\n\n- [[086_刺客列传|086 刺客列传]]（主要出处，含曹沫、专诸、豫让、聂政、荆轲）\n\n## 相关人物\n\n- [[高渐离]]（挚友，击筑送行，后以筑击秦始皇）\n- [[太子丹]]（主君，礼遇荆轲，供太牢车骑美女以顺其意）\n- [[樊於期]]（自刭献首，成全荆轲计划）\n- [[夏无且]]（刺秦时以药囊击荆轲）\n\n---\n\n[^life]: 生年推断参见[《荆轲生卒年推断》](../../doc/lifespan_inference/战国/燕荆轲.md)（置信度：低，约前312—前243年生）。\n\n## 生平大事 (自 kg 事件索引)\n\n- 约公元前228年 · 田光荐荆轲自刎  [`086-014`]\n- 约公元前228年 · 樊於期献首  [`086-015`]\n- （公元前227年） · 易水送别（易水）  [`086-016`]\n- （公元前227年） · 荆轲刺秦王（咸阳宫）  [`086-017`]\n\n## 史记引文\n\n《史记》中出现 **77** 处（标注符号：〖@荆轲〗）。\n\n**章节分布：**\n\n- [[006_秦始皇本纪|秦始皇本纪]]：§27.1、§27.2、§34.4\n- [[015_六国年表|六国年表]]：§r250\n- [[034_燕召公世家|燕召公世家]]：§22.1\n- [[044_魏世家|魏世家]]：§73\n- [[046_田敬仲完世家|田敬仲完世家]]：§26.2\n- [[073_白起王翦列传|白起王翦列传]]：§9\n- [[083_鲁仲连邹阳列传|鲁仲连邹阳列传]]：§16、§18、§21、§23\n- [[086_刺客列传|刺客列传]]：§24、§25、§26、§27、§28、§29、§36、§37 等共 23 处\n- [[088_蒙恬列传|蒙恬列传]]：§7\n- [[110_匈奴列传|匈奴列传]]：§16\n\n**引文摘录（共 77 处，下列仅示 5 条）：**\n\n> 出自 [[006_秦始皇本纪|秦始皇本纪]] §27.1：二十年，燕太子丹患秦兵至国，恐，使**荆轲**刺秦王。\n>\n> 出自 [[006_秦始皇本纪|秦始皇本纪]] §27.2：秦王觉之，体解**荆轲**以徇，而使王翦、辛胜攻燕。\n>\n> 出自 [[015_六国年表|六国年表]] §r250：|  [r250]  |    |  二十。太子丹使**荆轲**刺王，觉之。王翦将击燕。  |  魏王魏假元年  |    |  代王赵嘉元年  |  …\n>\n> 出自 [[034_燕召公世家|燕召公世家]] §22.1：燕见秦且灭六国，秦兵临易水，祸且至燕。太子燕太子丹阴养壮士二十人，使**荆轲**献督亢地图於秦，因袭刺秦王。秦王觉，杀荆轲，使将军王翦击燕。二十九年，秦攻拔我蓟，燕王亡…\n>\n> 出自 [[044_魏世家|魏世家]] §73：王假元年，燕太子燕太子丹使**荆轲**刺秦王，秦王觉之。\n\n"
    },
    {
      "rev_id": "20260425-133013-cca258",
      "timestamp": "2026-04-25T13:30:13Z",
      "author": "butler",
      "summary": "H4: 从生平大事索引推导pn字段",
      "parent_rev": "20260425-131127-08b741",
      "content_hash": "sha256:cca258e4439ee47cebf4b65c7c6c49a14358ad7172f9e8ca2e11143035f69d72",
      "size": 5691,
      "content": "---\nid: 荆轲\ntype: person\nlabel: 荆轲\npn: (086-014)\nsources: [刺客列传, 秦始皇本纪, 六国年表]\ndescription: \"荆轲（？— 前 227），卫人，游历至燕，燕人称'荆卿'； 性沈深好书，嗜酒，与高渐离为友； 燕太子丹礼待，受命刺秦王—— 以樊於期首级和燕督亢地图为信物， 图穷匕见，未能刺中，身被八创，倚柱而笑，骂…\"\naliases: [荆轲, 荆卿, 庆卿]\ncanonical_name: 荆轲\nbirth_ce: -?\ndeath_ce: -227\ntags: [战国, 燕国, 刺客, 图穷匕见, 易水送别, 列传人物]\nfeatured: true\n---\n# 荆轲\n\n[[荆轲]]（？— 前 227），卫人，游历至燕，燕人称\"荆卿\"；\n性沈深好书，嗜酒，与高渐离为友；\n燕太子丹礼待，受命刺秦王——\n以**樊於期首级**和**燕督亢地图**为信物，\n图穷匕见，未能刺中，身被八创，倚柱而笑，骂曰欲生劫之以得约契报太子；\n左右杀轲，刺秦失败。\n\n《史记》主要记载见[[086_刺客列传|086 刺客列传]]。\n\n---\n\n## 生平\n\n### 易水送别 · 风萧萧兮\n\n太子丹患秦进逼，荆轲请得樊於期首级与燕督亢地图——\n\n> 太子及宾客知其事者，皆白衣冠以送之。至易水之上，既祖，取道，高渐离击筑，荆轲和而歌，为变徵之声，士皆垂泪涕泣。又前而为歌曰：\"风萧萧兮易水寒，壮士一去兮不复还！\"复为羽声慷慨，士皆瞋目，发尽上指冠。於是荆轲就车而去，终已不顾。（[[086_刺客列传|086-033]]）\n\n### 图穷匕见 · 倚柱而笑\n\n至秦，以地图献秦王——\n\n> 荆轲奉樊於期头函，而秦舞阳奉地图柙，以次进。至陛，秦舞阳色变振恐，群臣怪之。荆轲顾笑舞阳，前谢曰：\"北蕃蛮夷之鄙人，未尝见天子，故振慴。原大王少假借之，使得毕使於前。\"秦王谓轲曰：\"取舞阳所持地图。\"轲既取图奏之，秦王发图，图穷而匕首见。因左手把秦王之袖，而右手持匕首揕之。未至身，秦王惊，自引而起，袖绝。（[[086_刺客列传|086-034]]）\n\n秦王环柱而走，群臣惶急失度，侍医[[夏无且]]以药囊投荆轲——秦王负剑拔之，断荆轲左股。\n\n> 轲自知事不就，倚柱而笑，箕踞以骂曰：\"事所以不成者，以欲生劫之，必得约契以报太子也。\"於是左右既前杀轲，秦王不怡者良久。（[[086_刺客列传|086-034]]）\n\n---\n\n## 太史公曰\n\n> 太史公曰：自曹沫至荆轲五人，此其义或成或不成，然其立意较然，不欺其志，名垂後世，岂妄也哉！（[[086_刺客列传|086-038]]）\n\n---\n\n## 对照表\n\n| 项目 | 内容 |\n| --- | --- |\n| 生年 | 不详（约前 312—前 243 年[^life]） |\n| 籍贯 | 卫（先祖为齐人，徙卫） |\n| 卒年 | 前 227 年（刺秦失败，被杀于咸阳宫） |\n| 关键事迹 | 易水送别、图穷匕见、倚柱骂曰 |\n| 主要传记 | [[086_刺客列传|086 刺客列传]] |\n\n---\n\n## 典故与成语\n\n- **图穷匕见** — 地图展开尽头，匕首显现；比喻阴谋败露\n- **风萧萧兮易水寒** — 千古悲歌，壮士诀别之词\n- **荆轲刺秦** — 中国历史上最著名的刺杀行动\n\n---\n\n## 相关章节\n\n- [[086_刺客列传|086 刺客列传]]（主要出处，含曹沫、专诸、豫让、聂政、荆轲）\n\n## 相关人物\n\n- [[高渐离]]（挚友，击筑送行，后以筑击秦始皇）\n- [[太子丹]]（主君，礼遇荆轲，供太牢车骑美女以顺其意）\n- [[樊於期]]（自刭献首，成全荆轲计划）\n- [[夏无且]]（刺秦时以药囊击荆轲）\n\n---\n\n[^life]: 生年推断参见[《荆轲生卒年推断》](../../doc/lifespan_inference/战国/燕荆轲.md)（置信度：低，约前312—前243年生）。\n\n## 生平大事 (自 kg 事件索引)\n\n- 约公元前228年 · 田光荐荆轲自刎  [`086-014`]\n- 约公元前228年 · 樊於期献首  [`086-015`]\n- （公元前227年） · 易水送别（易水）  [`086-016`]\n- （公元前227年） · 荆轲刺秦王（咸阳宫）  [`086-017`]\n\n## 史记引文\n\n《史记》中出现 **77** 处（标注符号：〖@荆轲〗）。\n\n**章节分布：**\n\n- [[006_秦始皇本纪|秦始皇本纪]]：§27.1、§27.2、§34.4\n- [[015_六国年表|六国年表]]：§r250\n- [[034_燕召公世家|燕召公世家]]：§22.1\n- [[044_魏世家|魏世家]]：§73\n- [[046_田敬仲完世家|田敬仲完世家]]：§26.2\n- [[073_白起王翦列传|白起王翦列传]]：§9\n- [[083_鲁仲连邹阳列传|鲁仲连邹阳列传]]：§16、§18、§21、§23\n- [[086_刺客列传|刺客列传]]：§24、§25、§26、§27、§28、§29、§36、§37 等共 23 处\n- [[088_蒙恬列传|蒙恬列传]]：§7\n- [[110_匈奴列传|匈奴列传]]：§16\n\n**引文摘录（共 77 处，下列仅示 5 条）：**\n\n> 出自 [[006_秦始皇本纪|秦始皇本纪]] §27.1：二十年，燕太子丹患秦兵至国，恐，使**荆轲**刺秦王。\n>\n> 出自 [[006_秦始皇本纪|秦始皇本纪]] §27.2：秦王觉之，体解**荆轲**以徇，而使王翦、辛胜攻燕。\n>\n> 出自 [[015_六国年表|六国年表]] §r250：|  [r250]  |    |  二十。太子丹使**荆轲**刺王，觉之。王翦将击燕。  |  魏王魏假元年  |    |  代王赵嘉元年  |  …\n>\n> 出自 [[034_燕召公世家|燕召公世家]] §22.1：燕见秦且灭六国，秦兵临易水，祸且至燕。太子燕太子丹阴养壮士二十人，使**荆轲**献督亢地图於秦，因袭刺秦王。秦王觉，杀荆轲，使将军王翦击燕。二十九年，秦攻拔我蓟，燕王亡…\n>\n> 出自 [[044_魏世家|魏世家]] §73：王假元年，燕太子燕太子丹使**荆轲**刺秦王，秦王觉之。\n\n",
      "size_before": 5677
    },
    {
      "rev_id": "20260425-131127-08b741",
      "timestamp": "2026-04-25T13:11:27Z",
      "author": "butler",
      "summary": "H4: 从wikilinks推导sources",
      "parent_rev": "20260425-124524-010b0e",
      "content_hash": "sha256:08b741b65b02adbfbaf5d19e0a8d0b46b4b1a725bef62efe14f8e078750d3172",
      "size": 5677,
      "content": "---\nid: 荆轲\ntype: person\nlabel: 荆轲\nsources: [刺客列传, 秦始皇本纪, 六国年表]\ndescription: \"荆轲（？— 前 227），卫人，游历至燕，燕人称'荆卿'； 性沈深好书，嗜酒，与高渐离为友； 燕太子丹礼待，受命刺秦王—— 以樊於期首级和燕督亢地图为信物， 图穷匕见，未能刺中，身被八创，倚柱而笑，骂…\"\naliases: [荆轲, 荆卿, 庆卿]\ncanonical_name: 荆轲\nbirth_ce: -?\ndeath_ce: -227\ntags: [战国, 燕国, 刺客, 图穷匕见, 易水送别, 列传人物]\nfeatured: true\n---\n# 荆轲\n\n[[荆轲]]（？— 前 227），卫人，游历至燕，燕人称\"荆卿\"；\n性沈深好书，嗜酒，与高渐离为友；\n燕太子丹礼待，受命刺秦王——\n以**樊於期首级**和**燕督亢地图**为信物，\n图穷匕见，未能刺中，身被八创，倚柱而笑，骂曰欲生劫之以得约契报太子；\n左右杀轲，刺秦失败。\n\n《史记》主要记载见[[086_刺客列传|086 刺客列传]]。\n\n---\n\n## 生平\n\n### 易水送别 · 风萧萧兮\n\n太子丹患秦进逼，荆轲请得樊於期首级与燕督亢地图——\n\n> 太子及宾客知其事者，皆白衣冠以送之。至易水之上，既祖，取道，高渐离击筑，荆轲和而歌，为变徵之声，士皆垂泪涕泣。又前而为歌曰：\"风萧萧兮易水寒，壮士一去兮不复还！\"复为羽声慷慨，士皆瞋目，发尽上指冠。於是荆轲就车而去，终已不顾。（[[086_刺客列传|086-033]]）\n\n### 图穷匕见 · 倚柱而笑\n\n至秦，以地图献秦王——\n\n> 荆轲奉樊於期头函，而秦舞阳奉地图柙，以次进。至陛，秦舞阳色变振恐，群臣怪之。荆轲顾笑舞阳，前谢曰：\"北蕃蛮夷之鄙人，未尝见天子，故振慴。原大王少假借之，使得毕使於前。\"秦王谓轲曰：\"取舞阳所持地图。\"轲既取图奏之，秦王发图，图穷而匕首见。因左手把秦王之袖，而右手持匕首揕之。未至身，秦王惊，自引而起，袖绝。（[[086_刺客列传|086-034]]）\n\n秦王环柱而走，群臣惶急失度，侍医[[夏无且]]以药囊投荆轲——秦王负剑拔之，断荆轲左股。\n\n> 轲自知事不就，倚柱而笑，箕踞以骂曰：\"事所以不成者，以欲生劫之，必得约契以报太子也。\"於是左右既前杀轲，秦王不怡者良久。（[[086_刺客列传|086-034]]）\n\n---\n\n## 太史公曰\n\n> 太史公曰：自曹沫至荆轲五人，此其义或成或不成，然其立意较然，不欺其志，名垂後世，岂妄也哉！（[[086_刺客列传|086-038]]）\n\n---\n\n## 对照表\n\n| 项目 | 内容 |\n| --- | --- |\n| 生年 | 不详（约前 312—前 243 年[^life]） |\n| 籍贯 | 卫（先祖为齐人，徙卫） |\n| 卒年 | 前 227 年（刺秦失败，被杀于咸阳宫） |\n| 关键事迹 | 易水送别、图穷匕见、倚柱骂曰 |\n| 主要传记 | [[086_刺客列传|086 刺客列传]] |\n\n---\n\n## 典故与成语\n\n- **图穷匕见** — 地图展开尽头，匕首显现；比喻阴谋败露\n- **风萧萧兮易水寒** — 千古悲歌，壮士诀别之词\n- **荆轲刺秦** — 中国历史上最著名的刺杀行动\n\n---\n\n## 相关章节\n\n- [[086_刺客列传|086 刺客列传]]（主要出处，含曹沫、专诸、豫让、聂政、荆轲）\n\n## 相关人物\n\n- [[高渐离]]（挚友，击筑送行，后以筑击秦始皇）\n- [[太子丹]]（主君，礼遇荆轲，供太牢车骑美女以顺其意）\n- [[樊於期]]（自刭献首，成全荆轲计划）\n- [[夏无且]]（刺秦时以药囊击荆轲）\n\n---\n\n[^life]: 生年推断参见[《荆轲生卒年推断》](../../doc/lifespan_inference/战国/燕荆轲.md)（置信度：低，约前312—前243年生）。\n\n## 生平大事 (自 kg 事件索引)\n\n- 约公元前228年 · 田光荐荆轲自刎  [`086-014`]\n- 约公元前228年 · 樊於期献首  [`086-015`]\n- （公元前227年） · 易水送别（易水）  [`086-016`]\n- （公元前227年） · 荆轲刺秦王（咸阳宫）  [`086-017`]\n\n## 史记引文\n\n《史记》中出现 **77** 处（标注符号：〖@荆轲〗）。\n\n**章节分布：**\n\n- [[006_秦始皇本纪|秦始皇本纪]]：§27.1、§27.2、§34.4\n- [[015_六国年表|六国年表]]：§r250\n- [[034_燕召公世家|燕召公世家]]：§22.1\n- [[044_魏世家|魏世家]]：§73\n- [[046_田敬仲完世家|田敬仲完世家]]：§26.2\n- [[073_白起王翦列传|白起王翦列传]]：§9\n- [[083_鲁仲连邹阳列传|鲁仲连邹阳列传]]：§16、§18、§21、§23\n- [[086_刺客列传|刺客列传]]：§24、§25、§26、§27、§28、§29、§36、§37 等共 23 处\n- [[088_蒙恬列传|蒙恬列传]]：§7\n- [[110_匈奴列传|匈奴列传]]：§16\n\n**引文摘录（共 77 处，下列仅示 5 条）：**\n\n> 出自 [[006_秦始皇本纪|秦始皇本纪]] §27.1：二十年，燕太子丹患秦兵至国，恐，使**荆轲**刺秦王。\n>\n> 出自 [[006_秦始皇本纪|秦始皇本纪]] §27.2：秦王觉之，体解**荆轲**以徇，而使王翦、辛胜攻燕。\n>\n> 出自 [[015_六国年表|六国年表]] §r250：|  [r250]  |    |  二十。太子丹使**荆轲**刺王，觉之。王翦将击燕。  |  魏王魏假元年  |    |  代王赵嘉元年  |  …\n>\n> 出自 [[034_燕召公世家|燕召公世家]] §22.1：燕见秦且灭六国，秦兵临易水，祸且至燕。太子燕太子丹阴养壮士二十人，使**荆轲**献督亢地图於秦，因袭刺秦王。秦王觉，杀荆轲，使将军王翦击燕。二十九年，秦攻拔我蓟，燕王亡…\n>\n> 出自 [[044_魏世家|魏世家]] §73：王假元年，燕太子燕太子丹使**荆轲**刺秦王，秦王觉之。\n\n",
      "size_before": 5623
    },
    {
      "rev_id": "20260425-124524-010b0e",
      "timestamp": "2026-04-25T12:45:24Z",
      "author": "butler",
      "summary": "H4: 添加 description 字段（首段推导）",
      "parent_rev": "20260425-122412-643516",
      "content_hash": "sha256:010b0e5f30534164abfdcea740c957cf10b9821f758705ecec690d9a79f99b5e",
      "size": 5623,
      "content": "---\nid: 荆轲\ntype: person\nlabel: 荆轲\ndescription: \"荆轲（？— 前 227），卫人，游历至燕，燕人称'荆卿'；\n性沈深好书，嗜酒，与高渐离为友；\n燕太子丹礼待，受命刺秦王——\n以樊於期首级和燕督亢地图为信物，\n图穷匕见，未能刺中，身被八创，倚柱而笑，骂…\"\naliases: [荆轲, 荆卿, 庆卿]\ncanonical_name: 荆轲\nbirth_ce: -?\ndeath_ce: -227\ntags: [战国, 燕国, 刺客, 图穷匕见, 易水送别, 列传人物]\nfeatured: true\n---\n\n# 荆轲\n\n[[荆轲]]（？— 前 227），卫人，游历至燕，燕人称\"荆卿\"；\n性沈深好书，嗜酒，与高渐离为友；\n燕太子丹礼待，受命刺秦王——\n以**樊於期首级**和**燕督亢地图**为信物，\n图穷匕见，未能刺中，身被八创，倚柱而笑，骂曰欲生劫之以得约契报太子；\n左右杀轲，刺秦失败。\n\n《史记》主要记载见[[086_刺客列传|086 刺客列传]]。\n\n---\n\n## 生平\n\n### 易水送别 · 风萧萧兮\n\n太子丹患秦进逼，荆轲请得樊於期首级与燕督亢地图——\n\n> 太子及宾客知其事者，皆白衣冠以送之。至易水之上，既祖，取道，高渐离击筑，荆轲和而歌，为变徵之声，士皆垂泪涕泣。又前而为歌曰：\"风萧萧兮易水寒，壮士一去兮不复还！\"复为羽声慷慨，士皆瞋目，发尽上指冠。於是荆轲就车而去，终已不顾。（[[086_刺客列传|086-033]]）\n\n### 图穷匕见 · 倚柱而笑\n\n至秦，以地图献秦王——\n\n> 荆轲奉樊於期头函，而秦舞阳奉地图柙，以次进。至陛，秦舞阳色变振恐，群臣怪之。荆轲顾笑舞阳，前谢曰：\"北蕃蛮夷之鄙人，未尝见天子，故振慴。原大王少假借之，使得毕使於前。\"秦王谓轲曰：\"取舞阳所持地图。\"轲既取图奏之，秦王发图，图穷而匕首见。因左手把秦王之袖，而右手持匕首揕之。未至身，秦王惊，自引而起，袖绝。（[[086_刺客列传|086-034]]）\n\n秦王环柱而走，群臣惶急失度，侍医[[夏无且]]以药囊投荆轲——秦王负剑拔之，断荆轲左股。\n\n> 轲自知事不就，倚柱而笑，箕踞以骂曰：\"事所以不成者，以欲生劫之，必得约契以报太子也。\"於是左右既前杀轲，秦王不怡者良久。（[[086_刺客列传|086-034]]）\n\n---\n\n## 太史公曰\n\n> 太史公曰：自曹沫至荆轲五人，此其义或成或不成，然其立意较然，不欺其志，名垂後世，岂妄也哉！（[[086_刺客列传|086-038]]）\n\n---\n\n## 对照表\n\n| 项目 | 内容 |\n| --- | --- |\n| 生年 | 不详（约前 312—前 243 年[^life]） |\n| 籍贯 | 卫（先祖为齐人，徙卫） |\n| 卒年 | 前 227 年（刺秦失败，被杀于咸阳宫） |\n| 关键事迹 | 易水送别、图穷匕见、倚柱骂曰 |\n| 主要传记 | [[086_刺客列传|086 刺客列传]] |\n\n---\n\n## 典故与成语\n\n- **图穷匕见** — 地图展开尽头，匕首显现；比喻阴谋败露\n- **风萧萧兮易水寒** — 千古悲歌，壮士诀别之词\n- **荆轲刺秦** — 中国历史上最著名的刺杀行动\n\n---\n\n## 相关章节\n\n- [[086_刺客列传|086 刺客列传]]（主要出处，含曹沫、专诸、豫让、聂政、荆轲）\n\n## 相关人物\n\n- [[高渐离]]（挚友，击筑送行，后以筑击秦始皇）\n- [[太子丹]]（主君，礼遇荆轲，供太牢车骑美女以顺其意）\n- [[樊於期]]（自刭献首，成全荆轲计划）\n- [[夏无且]]（刺秦时以药囊击荆轲）\n\n---\n\n[^life]: 生年推断参见[《荆轲生卒年推断》](../../doc/lifespan_inference/战国/燕荆轲.md)（置信度：低，约前312—前243年生）。\n\n## 生平大事 (自 kg 事件索引)\n\n- 约公元前228年 · 田光荐荆轲自刎  [`086-014`]\n- 约公元前228年 · 樊於期献首  [`086-015`]\n- （公元前227年） · 易水送别（易水）  [`086-016`]\n- （公元前227年） · 荆轲刺秦王（咸阳宫）  [`086-017`]\n\n## 史记引文\n\n《史记》中出现 **77** 处（标注符号：〖@荆轲〗）。\n\n**章节分布：**\n\n- [[006_秦始皇本纪|秦始皇本纪]]：§27.1、§27.2、§34.4\n- [[015_六国年表|六国年表]]：§r250\n- [[034_燕召公世家|燕召公世家]]：§22.1\n- [[044_魏世家|魏世家]]：§73\n- [[046_田敬仲完世家|田敬仲完世家]]：§26.2\n- [[073_白起王翦列传|白起王翦列传]]：§9\n- [[083_鲁仲连邹阳列传|鲁仲连邹阳列传]]：§16、§18、§21、§23\n- [[086_刺客列传|刺客列传]]：§24、§25、§26、§27、§28、§29、§36、§37 等共 23 处\n- [[088_蒙恬列传|蒙恬列传]]：§7\n- [[110_匈奴列传|匈奴列传]]：§16\n\n**引文摘录（共 77 处，下列仅示 5 条）：**\n\n> 出自 [[006_秦始皇本纪|秦始皇本纪]] §27.1：二十年，燕太子丹患秦兵至国，恐，使**荆轲**刺秦王。\n>\n> 出自 [[006_秦始皇本纪|秦始皇本纪]] §27.2：秦王觉之，体解**荆轲**以徇，而使王翦、辛胜攻燕。\n>\n> 出自 [[015_六国年表|六国年表]] §r250：|  [r250]  |    |  二十。太子丹使**荆轲**刺王，觉之。王翦将击燕。  |  魏王魏假元年  |    |  代王赵嘉元年  |  …\n>\n> 出自 [[034_燕召公世家|燕召公世家]] §22.1：燕见秦且灭六国，秦兵临易水，祸且至燕。太子燕太子丹阴养壮士二十人，使**荆轲**献督亢地图於秦，因袭刺秦王。秦王觉，杀荆轲，使将军王翦击燕。二十九年，秦攻拔我蓟，燕王亡…\n>\n> 出自 [[044_魏世家|魏世家]] §73：王假元年，燕太子燕太子丹使**荆轲**刺秦王，秦王觉之。\n\n",
      "size_before": 5326
    },
    {
      "rev_id": "20260425-122412-643516",
      "timestamp": "2026-04-25T12:24:12Z",
      "author": "butler",
      "summary": "butler/import-person: 更新史记引文 荆轲",
      "parent_rev": "20260425-050638-ba1318",
      "content_hash": "sha256:643516df524cb55f63e766dde78ee3cbaa6700e295492a1fefb119c0327916e4",
      "size": 5326,
      "content": "---\nid: 荆轲\ntype: person\nlabel: 荆轲\naliases: [荆轲, 荆卿, 庆卿]\ncanonical_name: 荆轲\nbirth_ce: -?\ndeath_ce: -227\ntags: [战国, 燕国, 刺客, 图穷匕见, 易水送别, 列传人物]\nfeatured: true\n---\n\n# 荆轲\n\n[[荆轲]]（？— 前 227），卫人，游历至燕，燕人称\"荆卿\"；\n性沈深好书，嗜酒，与高渐离为友；\n燕太子丹礼待，受命刺秦王——\n以**樊於期首级**和**燕督亢地图**为信物，\n图穷匕见，未能刺中，身被八创，倚柱而笑，骂曰欲生劫之以得约契报太子；\n左右杀轲，刺秦失败。\n\n《史记》主要记载见[[086_刺客列传|086 刺客列传]]。\n\n---\n\n## 生平\n\n### 易水送别 · 风萧萧兮\n\n太子丹患秦进逼，荆轲请得樊於期首级与燕督亢地图——\n\n> 太子及宾客知其事者，皆白衣冠以送之。至易水之上，既祖，取道，高渐离击筑，荆轲和而歌，为变徵之声，士皆垂泪涕泣。又前而为歌曰：\"风萧萧兮易水寒，壮士一去兮不复还！\"复为羽声慷慨，士皆瞋目，发尽上指冠。於是荆轲就车而去，终已不顾。（[[086_刺客列传|086-033]]）\n\n### 图穷匕见 · 倚柱而笑\n\n至秦，以地图献秦王——\n\n> 荆轲奉樊於期头函，而秦舞阳奉地图柙，以次进。至陛，秦舞阳色变振恐，群臣怪之。荆轲顾笑舞阳，前谢曰：\"北蕃蛮夷之鄙人，未尝见天子，故振慴。原大王少假借之，使得毕使於前。\"秦王谓轲曰：\"取舞阳所持地图。\"轲既取图奏之，秦王发图，图穷而匕首见。因左手把秦王之袖，而右手持匕首揕之。未至身，秦王惊，自引而起，袖绝。（[[086_刺客列传|086-034]]）\n\n秦王环柱而走，群臣惶急失度，侍医[[夏无且]]以药囊投荆轲——秦王负剑拔之，断荆轲左股。\n\n> 轲自知事不就，倚柱而笑，箕踞以骂曰：\"事所以不成者，以欲生劫之，必得约契以报太子也。\"於是左右既前杀轲，秦王不怡者良久。（[[086_刺客列传|086-034]]）\n\n---\n\n## 太史公曰\n\n> 太史公曰：自曹沫至荆轲五人，此其义或成或不成，然其立意较然，不欺其志，名垂後世，岂妄也哉！（[[086_刺客列传|086-038]]）\n\n---\n\n## 对照表\n\n| 项目 | 内容 |\n| --- | --- |\n| 生年 | 不详（约前 312—前 243 年[^life]） |\n| 籍贯 | 卫（先祖为齐人，徙卫） |\n| 卒年 | 前 227 年（刺秦失败，被杀于咸阳宫） |\n| 关键事迹 | 易水送别、图穷匕见、倚柱骂曰 |\n| 主要传记 | [[086_刺客列传|086 刺客列传]] |\n\n---\n\n## 典故与成语\n\n- **图穷匕见** — 地图展开尽头，匕首显现；比喻阴谋败露\n- **风萧萧兮易水寒** — 千古悲歌，壮士诀别之词\n- **荆轲刺秦** — 中国历史上最著名的刺杀行动\n\n---\n\n## 相关章节\n\n- [[086_刺客列传|086 刺客列传]]（主要出处，含曹沫、专诸、豫让、聂政、荆轲）\n\n## 相关人物\n\n- [[高渐离]]（挚友，击筑送行，后以筑击秦始皇）\n- [[太子丹]]（主君，礼遇荆轲，供太牢车骑美女以顺其意）\n- [[樊於期]]（自刭献首，成全荆轲计划）\n- [[夏无且]]（刺秦时以药囊击荆轲）\n\n---\n\n[^life]: 生年推断参见[《荆轲生卒年推断》](../../doc/lifespan_inference/战国/燕荆轲.md)（置信度：低，约前312—前243年生）。\n\n## 生平大事 (自 kg 事件索引)\n\n- 约公元前228年 · 田光荐荆轲自刎  [`086-014`]\n- 约公元前228年 · 樊於期献首  [`086-015`]\n- （公元前227年） · 易水送别（易水）  [`086-016`]\n- （公元前227年） · 荆轲刺秦王（咸阳宫）  [`086-017`]\n\n## 史记引文\n\n《史记》中出现 **77** 处（标注符号：〖@荆轲〗）。\n\n**章节分布：**\n\n- [[006_秦始皇本纪|秦始皇本纪]]：§27.1、§27.2、§34.4\n- [[015_六国年表|六国年表]]：§r250\n- [[034_燕召公世家|燕召公世家]]：§22.1\n- [[044_魏世家|魏世家]]：§73\n- [[046_田敬仲完世家|田敬仲完世家]]：§26.2\n- [[073_白起王翦列传|白起王翦列传]]：§9\n- [[083_鲁仲连邹阳列传|鲁仲连邹阳列传]]：§16、§18、§21、§23\n- [[086_刺客列传|刺客列传]]：§24、§25、§26、§27、§28、§29、§36、§37 等共 23 处\n- [[088_蒙恬列传|蒙恬列传]]：§7\n- [[110_匈奴列传|匈奴列传]]：§16\n\n**引文摘录（共 77 处，下列仅示 5 条）：**\n\n> 出自 [[006_秦始皇本纪|秦始皇本纪]] §27.1：二十年，燕太子丹患秦兵至国，恐，使**荆轲**刺秦王。\n>\n> 出自 [[006_秦始皇本纪|秦始皇本纪]] §27.2：秦王觉之，体解**荆轲**以徇，而使王翦、辛胜攻燕。\n>\n> 出自 [[015_六国年表|六国年表]] §r250：|  [r250]  |    |  二十。太子丹使**荆轲**刺王，觉之。王翦将击燕。  |  魏王魏假元年  |    |  代王赵嘉元年  |  …\n>\n> 出自 [[034_燕召公世家|燕召公世家]] §22.1：燕见秦且灭六国，秦兵临易水，祸且至燕。太子燕太子丹阴养壮士二十人，使**荆轲**献督亢地图於秦，因袭刺秦王。秦王觉，杀荆轲，使将军王翦击燕。二十九年，秦攻拔我蓟，燕王亡…\n>\n> 出自 [[044_魏世家|魏世家]] §73：王假元年，燕太子燕太子丹使**荆轲**刺秦王，秦王觉之。\n\n",
      "size_before": 3676
    },
    {
      "rev_id": "20260425-050638-ba1318",
      "timestamp": "2026-04-25T05:06:38Z",
      "author": "butler",
      "summary": "add-event-timeline: backfill revision",
      "parent_rev": "20260424-175104-cc7fe9",
      "content_hash": "sha256:ba1318064d5546e91fa67e169dc44cc01ac4c6fd6ea378dc3f5a72072776ca46",
      "size": 3676,
      "content": "---\nid: 荆轲\ntype: person\nlabel: 荆轲\naliases: [荆轲, 荆卿, 庆卿]\ncanonical_name: 荆轲\nbirth_ce: -?\ndeath_ce: -227\ntags: [战国, 燕国, 刺客, 图穷匕见, 易水送别, 列传人物]\nfeatured: true\n---\n\n# 荆轲\n\n[[荆轲]]（？— 前 227），卫人，游历至燕，燕人称\"荆卿\"；\n性沈深好书，嗜酒，与高渐离为友；\n燕太子丹礼待，受命刺秦王——\n以**樊於期首级**和**燕督亢地图**为信物，\n图穷匕见，未能刺中，身被八创，倚柱而笑，骂曰欲生劫之以得约契报太子；\n左右杀轲，刺秦失败。\n\n《史记》主要记载见[[086_刺客列传|086 刺客列传]]。\n\n---\n\n## 生平\n\n### 易水送别 · 风萧萧兮\n\n太子丹患秦进逼，荆轲请得樊於期首级与燕督亢地图——\n\n> 太子及宾客知其事者，皆白衣冠以送之。至易水之上，既祖，取道，高渐离击筑，荆轲和而歌，为变徵之声，士皆垂泪涕泣。又前而为歌曰：\"风萧萧兮易水寒，壮士一去兮不复还！\"复为羽声慷慨，士皆瞋目，发尽上指冠。於是荆轲就车而去，终已不顾。（[[086_刺客列传|086-033]]）\n\n### 图穷匕见 · 倚柱而笑\n\n至秦，以地图献秦王——\n\n> 荆轲奉樊於期头函，而秦舞阳奉地图柙，以次进。至陛，秦舞阳色变振恐，群臣怪之。荆轲顾笑舞阳，前谢曰：\"北蕃蛮夷之鄙人，未尝见天子，故振慴。原大王少假借之，使得毕使於前。\"秦王谓轲曰：\"取舞阳所持地图。\"轲既取图奏之，秦王发图，图穷而匕首见。因左手把秦王之袖，而右手持匕首揕之。未至身，秦王惊，自引而起，袖绝。（[[086_刺客列传|086-034]]）\n\n秦王环柱而走，群臣惶急失度，侍医[[夏无且]]以药囊投荆轲——秦王负剑拔之，断荆轲左股。\n\n> 轲自知事不就，倚柱而笑，箕踞以骂曰：\"事所以不成者，以欲生劫之，必得约契以报太子也。\"於是左右既前杀轲，秦王不怡者良久。（[[086_刺客列传|086-034]]）\n\n---\n\n## 太史公曰\n\n> 太史公曰：自曹沫至荆轲五人，此其义或成或不成，然其立意较然，不欺其志，名垂後世，岂妄也哉！（[[086_刺客列传|086-038]]）\n\n---\n\n## 对照表\n\n| 项目 | 内容 |\n| --- | --- |\n| 生年 | 不详（约前 312—前 243 年[^life]） |\n| 籍贯 | 卫（先祖为齐人，徙卫） |\n| 卒年 | 前 227 年（刺秦失败，被杀于咸阳宫） |\n| 关键事迹 | 易水送别、图穷匕见、倚柱骂曰 |\n| 主要传记 | [[086_刺客列传|086 刺客列传]] |\n\n---\n\n## 典故与成语\n\n- **图穷匕见** — 地图展开尽头，匕首显现；比喻阴谋败露\n- **风萧萧兮易水寒** — 千古悲歌，壮士诀别之词\n- **荆轲刺秦** — 中国历史上最著名的刺杀行动\n\n---\n\n## 相关章节\n\n- [[086_刺客列传|086 刺客列传]]（主要出处，含曹沫、专诸、豫让、聂政、荆轲）\n\n## 相关人物\n\n- [[高渐离]]（挚友，击筑送行，后以筑击秦始皇）\n- [[太子丹]]（主君，礼遇荆轲，供太牢车骑美女以顺其意）\n- [[樊於期]]（自刭献首，成全荆轲计划）\n- [[夏无且]]（刺秦时以药囊击荆轲）\n\n---\n\n[^life]: 生年推断参见[《荆轲生卒年推断》](../../doc/lifespan_inference/战国/燕荆轲.md)（置信度：低，约前312—前243年生）。\n\n## 生平大事 (自 kg 事件索引)\n\n- 约公元前228年 · 田光荐荆轲自刎  [`086-014`]\n- 约公元前228年 · 樊於期献首  [`086-015`]\n- （公元前227年） · 易水送别（易水）  [`086-016`]\n- （公元前227年） · 荆轲刺秦王（咸阳宫）  [`086-017`]\n",
      "size_before": 3374
    },
    {
      "rev_id": "20260424-175104-cc7fe9",
      "timestamp": "2026-04-24T17:51:04Z",
      "author": "butler",
      "summary": "R2150 cite-doc-report: 荆轲 生年[^life]引注",
      "parent_rev": "20260423-050532-af54b1",
      "content_hash": "sha256:cc7fe90d0235fb8293bcca8f03339ea932d1ed834373d3e0762c5af7e63a270b",
      "size": 3374,
      "content": "---\nid: 荆轲\ntype: person\nlabel: 荆轲\naliases: [荆轲, 荆卿, 庆卿]\ncanonical_name: 荆轲\nbirth_ce: -?\ndeath_ce: -227\ntags: [战国, 燕国, 刺客, 图穷匕见, 易水送别]\nfeatured: true\n---\n\n# 荆轲\n\n[[荆轲]]（？— 前 227），卫人，游历至燕，燕人称\"荆卿\"；\n性沈深好书，嗜酒，与高渐离为友；\n燕太子丹礼待，受命刺秦王——\n以**樊於期首级**和**燕督亢地图**为信物，\n图穷匕见，未能刺中，身被八创，倚柱而笑，骂曰欲生劫之以得约契报太子；\n左右杀轲，刺秦失败。\n\n《史记》主要记载见[[086_刺客列传|086 刺客列传]]。\n\n---\n\n## 生平\n\n### 易水送别 · 风萧萧兮\n\n太子丹患秦进逼，荆轲请得樊於期首级与燕督亢地图——\n\n> 太子及宾客知其事者，皆白衣冠以送之。至易水之上，既祖，取道，高渐离击筑，荆轲和而歌，为变徵之声，士皆垂泪涕泣。又前而为歌曰：\"风萧萧兮易水寒，壮士一去兮不复还！\"复为羽声慷慨，士皆瞋目，发尽上指冠。於是荆轲就车而去，终已不顾。（[[086_刺客列传|086-033]]）\n\n### 图穷匕见 · 倚柱而笑\n\n至秦，以地图献秦王——\n\n> 荆轲奉樊於期头函，而秦舞阳奉地图柙，以次进。至陛，秦舞阳色变振恐，群臣怪之。荆轲顾笑舞阳，前谢曰：\"北蕃蛮夷之鄙人，未尝见天子，故振慴。原大王少假借之，使得毕使於前。\"秦王谓轲曰：\"取舞阳所持地图。\"轲既取图奏之，秦王发图，图穷而匕首见。因左手把秦王之袖，而右手持匕首揕之。未至身，秦王惊，自引而起，袖绝。（[[086_刺客列传|086-034]]）\n\n秦王环柱而走，群臣惶急失度，侍医[[夏无且]]以药囊投荆轲——秦王负剑拔之，断荆轲左股。\n\n> 轲自知事不就，倚柱而笑，箕踞以骂曰：\"事所以不成者，以欲生劫之，必得约契以报太子也。\"於是左右既前杀轲，秦王不怡者良久。（[[086_刺客列传|086-034]]）\n\n---\n\n## 太史公曰\n\n> 太史公曰：自曹沫至荆轲五人，此其义或成或不成，然其立意较然，不欺其志，名垂後世，岂妄也哉！（[[086_刺客列传|086-038]]）\n\n---\n\n## 对照表\n\n| 项目 | 内容 |\n| --- | --- |\n| 生年 | 不详（约前 312—前 243 年[^life]） |\n| 籍贯 | 卫（先祖为齐人，徙卫） |\n| 卒年 | 前 227 年（刺秦失败，被杀于咸阳宫） |\n| 关键事迹 | 易水送别、图穷匕见、倚柱骂曰 |\n| 主要传记 | [[086_刺客列传|086 刺客列传]] |\n\n---\n\n## 典故与成语\n\n- **图穷匕见** — 地图展开尽头，匕首显现；比喻阴谋败露\n- **风萧萧兮易水寒** — 千古悲歌，壮士诀别之词\n- **荆轲刺秦** — 中国历史上最著名的刺杀行动\n\n---\n\n## 相关章节\n\n- [[086_刺客列传|086 刺客列传]]（主要出处，含曹沫、专诸、豫让、聂政、荆轲）\n\n## 相关人物\n\n- [[高渐离]]（挚友，击筑送行，后以筑击秦始皇）\n- [[太子丹]]（主君，礼遇荆轲，供太牢车骑美女以顺其意）\n- [[樊於期]]（自刭献首，成全荆轲计划）\n- [[夏无且]]（刺秦时以药囊击荆轲）\n\n---\n\n[^life]: 生年推断参见[《荆轲生卒年推断》](../../doc/lifespan_inference/战国/燕荆轲.md)（置信度：低，约前312—前243年生）。\n",
      "size_before": 3236
    },
    {
      "rev_id": "20260423-050532-af54b1",
      "timestamp": "2026-04-23T05:05:32Z",
      "author": "butler",
      "summary": "butler edit",
      "parent_rev": "20260423-015003-b86311",
      "content_hash": "sha256:af54b1c451b7a4b64b743ec3dfd8a7beb52b9e83735a40979d58d03f1b51645a",
      "size": 3236,
      "content": "---\nid: 荆轲\ntype: person\nlabel: 荆轲\naliases: [荆轲, 荆卿, 庆卿]\ncanonical_name: 荆轲\nbirth_ce: -?\ndeath_ce: -227\ntags: [战国, 燕国, 刺客, 图穷匕见, 易水送别]\nfeatured: true\n---\n\n# 荆轲\n\n[[荆轲]]（？— 前 227），卫人，游历至燕，燕人称\"荆卿\"；\n性沈深好书，嗜酒，与高渐离为友；\n燕太子丹礼待，受命刺秦王——\n以**樊於期首级**和**燕督亢地图**为信物，\n图穷匕见，未能刺中，身被八创，倚柱而笑，骂曰欲生劫之以得约契报太子；\n左右杀轲，刺秦失败。\n\n《史记》主要记载见[[086_刺客列传|086 刺客列传]]。\n\n---\n\n## 生平\n\n### 易水送别 · 风萧萧兮\n\n太子丹患秦进逼，荆轲请得樊於期首级与燕督亢地图——\n\n> 太子及宾客知其事者，皆白衣冠以送之。至易水之上，既祖，取道，高渐离击筑，荆轲和而歌，为变徵之声，士皆垂泪涕泣。又前而为歌曰：\"风萧萧兮易水寒，壮士一去兮不复还！\"复为羽声慷慨，士皆瞋目，发尽上指冠。於是荆轲就车而去，终已不顾。（[[086_刺客列传|086-033]]）\n\n### 图穷匕见 · 倚柱而笑\n\n至秦，以地图献秦王——\n\n> 荆轲奉樊於期头函，而秦舞阳奉地图柙，以次进。至陛，秦舞阳色变振恐，群臣怪之。荆轲顾笑舞阳，前谢曰：\"北蕃蛮夷之鄙人，未尝见天子，故振慴。原大王少假借之，使得毕使於前。\"秦王谓轲曰：\"取舞阳所持地图。\"轲既取图奏之，秦王发图，图穷而匕首见。因左手把秦王之袖，而右手持匕首揕之。未至身，秦王惊，自引而起，袖绝。（[[086_刺客列传|086-034]]）\n\n秦王环柱而走，群臣惶急失度，侍医[[夏无且]]以药囊投荆轲——秦王负剑拔之，断荆轲左股。\n\n> 轲自知事不就，倚柱而笑，箕踞以骂曰：\"事所以不成者，以欲生劫之，必得约契以报太子也。\"於是左右既前杀轲，秦王不怡者良久。（[[086_刺客列传|086-034]]）\n\n---\n\n## 太史公曰\n\n> 太史公曰：自曹沫至荆轲五人，此其义或成或不成，然其立意较然，不欺其志，名垂後世，岂妄也哉！（[[086_刺客列传|086-038]]）\n\n---\n\n## 对照表\n\n| 项目 | 内容 |\n| --- | --- |\n| 籍贯 | 卫（先祖为齐人，徙卫） |\n| 卒年 | 前 227 年（刺秦失败，被杀于咸阳宫） |\n| 关键事迹 | 易水送别、图穷匕见、倚柱骂曰 |\n| 主要传记 | [[086_刺客列传|086 刺客列传]] |\n\n---\n\n## 典故与成语\n\n- **图穷匕见** — 地图展开尽头，匕首显现；比喻阴谋败露\n- **风萧萧兮易水寒** — 千古悲歌，壮士诀别之词\n- **荆轲刺秦** — 中国历史上最著名的刺杀行动\n\n---\n\n## 相关章节\n\n- [[086_刺客列传|086 刺客列传]]（主要出处，含曹沫、专诸、豫让、聂政、荆轲）\n\n## 相关人物\n\n- [[高渐离]]（挚友，击筑送行，后以筑击秦始皇）\n- [[太子丹]]（主君，礼遇荆轲，供太牢车骑美女以顺其意）\n- [[樊於期]]（自刭献首，成全荆轲计划）\n- [[夏无且]]（刺秦时以药囊击荆轲）\n\n---\n\n*外部索引*: [person.html#荆轲](../../docs/entities/person.html#荆轲)\n",
      "size_before": 2988
    },
    {
      "rev_id": "20260423-015003-b86311",
      "timestamp": "2026-04-23T01:50:03Z",
      "author": "butler",
      "summary": "butler/R79: 精品页/stub/深化/链接强化",
      "parent_rev": "20260422-231724-930438",
      "content_hash": "sha256:b8631112fe7ff1f0411ee5123becf6be78841560c0bed5fbe9ee7c2070f646c6",
      "size": 2988,
      "content": "---\nid: 荆轲\ntype: person\nlabel: 荆轲\naliases: [荆轲, 荆卿, 庆卿]\ncanonical_name: 荆轲\nbirth_ce: -?\ndeath_ce: -227\ntags: [战国, 燕国, 刺客, 图穷匕见, 易水送别]\nfeatured: true\n---\n\n# 荆轲\n\n[[荆轲]]（？— 前 227），卫人，游历至燕，燕人称\"荆卿\"；\n性沈深好书，嗜酒，与高渐离为友；\n燕太子丹礼待，受命刺秦王——\n以**樊於期首级**和**燕督亢地图**为信物，\n图穷匕见，未能刺中，身被八创，倚柱而笑，骂曰欲生劫之以得约契报太子；\n左右杀轲，刺秦失败。\n\n《史记》主要记载见[[086_刺客列传|086 刺客列传]]。\n\n---\n\n## 生平\n\n### 易水送别 · 风萧萧兮\n\n太子丹患秦进逼，荆轲请得樊於期首级与燕督亢地图——\n\n> 太子及宾客知其事者，皆白衣冠以送之。至易水之上，既祖，取道，高渐离击筑，荆轲和而歌，为变徵之声，士皆垂泪涕泣。又前而为歌曰：\"风萧萧兮易水寒，壮士一去兮不复还！\"复为羽声慷慨，士皆瞋目，发尽上指冠。於是荆轲就车而去，终已不顾。（[[086_刺客列传|086-045]]）\n\n### 图穷匕见 · 倚柱而笑\n\n至秦，以地图献秦王——\n\n> 荆轲奉樊於期头函，而秦舞阳奉地图柙，以次进。至陛，秦舞阳色变振恐……轲既取图奏之，秦王发图，图穷而匕首见。因左手把秦王之袖，而右手持匕首揕之。未至身，秦王惊，自引而起，袖绝。（[[086_刺客列传|086-050]]）\n\n秦王环柱而走，群臣惶急失度，侍医夏无且以药囊投荆轲——秦王负剑拔之，断荆轲左股。\n\n> 轲自知事不就，倚柱而笑，箕踞以骂曰：\"事所以不成者，以欲生劫之，必得约契以报太子也。\"於是左右既前杀轲，秦王不怡者良久。（[[086_刺客列传|086-035]]）\n\n---\n\n## 太史公曰\n\n> 太史公曰：自曹沫至荆轲五人，此其义或成或不成，然其立意较然，不欺其志，名垂後世，岂妄也哉！（[[086_刺客列传|086-039]]）\n\n---\n\n## 对照表\n\n| 项目 | 内容 |\n| --- | --- |\n| 籍贯 | 卫（先祖为齐人，徙卫） |\n| 卒年 | 前 227 年（刺秦失败，被杀于咸阳宫） |\n| 关键事迹 | 易水送别、图穷匕见、倚柱骂曰 |\n| 主要传记 | [[086_刺客列传|086 刺客列传]] |\n\n---\n\n## 典故与成语\n\n- **图穷匕见** — 地图展开尽头，匕首显现；比喻阴谋败露\n- **风萧萧兮易水寒** — 千古悲歌，壮士诀别之词\n- **荆轲刺秦** — 中国历史上最著名的刺杀行动\n\n---\n\n## 相关章节\n\n- [[086_刺客列传|086 刺客列传]]（主要出处，含曹沫、专诸、豫让、聂政、荆轲）\n\n## 相关人物\n\n- 高渐离（挚友，击筑送行，后以筑击秦始皇）\n- [[燕太子丹]]（主君，礼遇荆轲，供太牢车骑美女以顺其意）\n- 樊於期（自刭献首，成全荆轲计划）\n\n---\n\n*外部索引*: [person.html#荆轲](../../docs/entities/person.html#荆轲)\n",
      "size_before": 2948
    },
    {
      "rev_id": "20260422-231724-930438",
      "timestamp": "2026-04-22T23:17:24Z",
      "author": "bot-lint",
      "summary": "bot-lint/citation-fix: 荆轲 （[[086_刺客列传|086-035]]）\n→50 (conf=1.00)",
      "parent_rev": "20260422-231724-85ac95",
      "content_hash": "sha256:93043858cf2069c801c88bc096d78c63a310bfed993e083281c7a7b55de94306",
      "size": 2948,
      "content": "---\nid: 荆轲\ntype: person\nlabel: 荆轲\naliases: [荆轲, 荆卿, 庆卿]\ncanonical_name: 荆轲\nbirth_ce: -?\ndeath_ce: -227\ntags: [战国, 燕国, 刺客, 图穷匕见, 易水送别]\nfeatured: true\n---\n\n# 荆轲\n\n[[荆轲]]（？— 前 227），卫人，游历至燕，燕人称\"荆卿\"；\n性沈深好书，嗜酒，与高渐离为友；\n燕太子丹礼待，受命刺秦王——\n以**樊於期首级**和**燕督亢地图**为信物，\n图穷匕见，未能刺中，身被八创，倚柱而笑，骂曰欲生劫之以得约契报太子；\n左右杀轲，刺秦失败。\n\n《史记》主要记载见[[086_刺客列传|086 刺客列传]]。\n\n---\n\n## 生平\n\n### 易水送别 · 风萧萧兮\n\n太子丹患秦进逼，荆轲请得樊於期首级与燕督亢地图——\n\n> 太子及宾客知其事者，皆白衣冠以送之。至易水之上，既祖，取道，高渐离击筑，荆轲和而歌，为变徵之声，士皆垂泪涕泣。又前而为歌曰：\"风萧萧兮易水寒，壮士一去兮不复还！\"复为羽声慷慨，士皆瞋目，发尽上指冠。於是荆轲就车而去，终已不顾。（[[086_刺客列传|086-045]]）\n\n### 图穷匕见 · 倚柱而笑\n\n至秦，以地图献秦王——\n\n> 荆轲奉樊於期头函，而秦舞阳奉地图柙，以次进。至陛，秦舞阳色变振恐……轲既取图奏之，秦王发图，图穷而匕首见。因左手把秦王之袖，而右手持匕首揕之。未至身，秦王惊，自引而起，袖绝。（[[086_刺客列传|086-050]]）\n\n秦王环柱而走，群臣惶急失度，侍医夏无且以药囊投荆轲——秦王负剑拔之，断荆轲左股。\n\n> 轲自知事不就，倚柱而笑，箕踞以骂曰：\"事所以不成者，以欲生劫之，必得约契以报太子也。\"於是左右既前杀轲，秦王不怡者良久。（[[086_刺客列传|086-035]]）\n\n---\n\n## 太史公曰\n\n> 太史公曰：自曹沫至荆轲五人，此其义或成或不成，然其立意较然，不欺其志，名垂後世，岂妄也哉！（[[086_刺客列传|086-039]]）\n\n---\n\n## 对照表\n\n| 项目 | 内容 |\n| --- | --- |\n| 籍贯 | 卫（先祖为齐人，徙卫） |\n| 卒年 | 前 227 年（刺秦失败，被杀于咸阳宫） |\n| 关键事迹 | 易水送别、图穷匕见、倚柱骂曰 |\n| 主要传记 | [[086_刺客列传|086 刺客列传]] |\n\n---\n\n## 典故与成语\n\n- **图穷匕见** — 地图展开尽头，匕首显现；比喻阴谋败露\n- **风萧萧兮易水寒** — 千古悲歌，壮士诀别之词\n- **荆轲刺秦** — 中国历史上最著名的刺杀行动\n\n---\n\n## 相关章节\n\n- [[086_刺客列传|086 刺客列传]]（主要出处，含曹沫、专诸、豫让、聂政、荆轲）\n\n## 相关人物\n\n- 高渐离（挚友，击筑送行，后以筑击秦始皇）\n- 燕太子丹（主君，礼遇荆轲）\n- 樊於期（自刭献首，成全荆轲计划）\n\n---\n\n*外部索引*: [person.html#荆轲](../../docs/entities/person.html#荆轲)\n",
      "size_before": 2948
    },
    {
      "rev_id": "20260422-231724-85ac95",
      "timestamp": "2026-04-22T23:17:24Z",
      "author": "bot-lint",
      "summary": "bot-lint/citation-fix: 荆轲 （[[086_刺客列传|086-034]]）\n→45 (conf=1.00)",
      "parent_rev": "20260422-223733-12a7ea",
      "content_hash": "sha256:85ac95861789d58d8b36eaed3a62d6bb08a5c7bad2839a9f48bd6d52dde2266f",
      "size": 2948,
      "content": "---\nid: 荆轲\ntype: person\nlabel: 荆轲\naliases: [荆轲, 荆卿, 庆卿]\ncanonical_name: 荆轲\nbirth_ce: -?\ndeath_ce: -227\ntags: [战国, 燕国, 刺客, 图穷匕见, 易水送别]\nfeatured: true\n---\n\n# 荆轲\n\n[[荆轲]]（？— 前 227），卫人，游历至燕，燕人称\"荆卿\"；\n性沈深好书，嗜酒，与高渐离为友；\n燕太子丹礼待，受命刺秦王——\n以**樊於期首级**和**燕督亢地图**为信物，\n图穷匕见，未能刺中，身被八创，倚柱而笑，骂曰欲生劫之以得约契报太子；\n左右杀轲，刺秦失败。\n\n《史记》主要记载见[[086_刺客列传|086 刺客列传]]。\n\n---\n\n## 生平\n\n### 易水送别 · 风萧萧兮\n\n太子丹患秦进逼，荆轲请得樊於期首级与燕督亢地图——\n\n> 太子及宾客知其事者，皆白衣冠以送之。至易水之上，既祖，取道，高渐离击筑，荆轲和而歌，为变徵之声，士皆垂泪涕泣。又前而为歌曰：\"风萧萧兮易水寒，壮士一去兮不复还！\"复为羽声慷慨，士皆瞋目，发尽上指冠。於是荆轲就车而去，终已不顾。（[[086_刺客列传|086-045]]）\n\n### 图穷匕见 · 倚柱而笑\n\n至秦，以地图献秦王——\n\n> 荆轲奉樊於期头函，而秦舞阳奉地图柙，以次进。至陛，秦舞阳色变振恐……轲既取图奏之，秦王发图，图穷而匕首见。因左手把秦王之袖，而右手持匕首揕之。未至身，秦王惊，自引而起，袖绝。（[[086_刺客列传|086-035]]）\n\n秦王环柱而走，群臣惶急失度，侍医夏无且以药囊投荆轲——秦王负剑拔之，断荆轲左股。\n\n> 轲自知事不就，倚柱而笑，箕踞以骂曰：\"事所以不成者，以欲生劫之，必得约契以报太子也。\"於是左右既前杀轲，秦王不怡者良久。（[[086_刺客列传|086-035]]）\n\n---\n\n## 太史公曰\n\n> 太史公曰：自曹沫至荆轲五人，此其义或成或不成，然其立意较然，不欺其志，名垂後世，岂妄也哉！（[[086_刺客列传|086-039]]）\n\n---\n\n## 对照表\n\n| 项目 | 内容 |\n| --- | --- |\n| 籍贯 | 卫（先祖为齐人，徙卫） |\n| 卒年 | 前 227 年（刺秦失败，被杀于咸阳宫） |\n| 关键事迹 | 易水送别、图穷匕见、倚柱骂曰 |\n| 主要传记 | [[086_刺客列传|086 刺客列传]] |\n\n---\n\n## 典故与成语\n\n- **图穷匕见** — 地图展开尽头，匕首显现；比喻阴谋败露\n- **风萧萧兮易水寒** — 千古悲歌，壮士诀别之词\n- **荆轲刺秦** — 中国历史上最著名的刺杀行动\n\n---\n\n## 相关章节\n\n- [[086_刺客列传|086 刺客列传]]（主要出处，含曹沫、专诸、豫让、聂政、荆轲）\n\n## 相关人物\n\n- 高渐离（挚友，击筑送行，后以筑击秦始皇）\n- 燕太子丹（主君，礼遇荆轲）\n- 樊於期（自刭献首，成全荆轲计划）\n\n---\n\n*外部索引*: [person.html#荆轲](../../docs/entities/person.html#荆轲)\n",
      "size_before": 2948
    },
    {
      "rev_id": "20260422-223733-12a7ea",
      "timestamp": "2026-04-22T22:37:33Z",
      "author": "butler",
      "summary": "butler edit",
      "parent_rev": null,
      "content_hash": "sha256:12a7eaa78666230065192b86669e487faa960a5d942fb9685c9db6fc108150fc",
      "size": 2948,
      "content": "---\nid: 荆轲\ntype: person\nlabel: 荆轲\naliases: [荆轲, 荆卿, 庆卿]\ncanonical_name: 荆轲\nbirth_ce: -?\ndeath_ce: -227\ntags: [战国, 燕国, 刺客, 图穷匕见, 易水送别]\nfeatured: true\n---\n\n# 荆轲\n\n[[荆轲]]（？— 前 227），卫人，游历至燕，燕人称\"荆卿\"；\n性沈深好书，嗜酒，与高渐离为友；\n燕太子丹礼待，受命刺秦王——\n以**樊於期首级**和**燕督亢地图**为信物，\n图穷匕见，未能刺中，身被八创，倚柱而笑，骂曰欲生劫之以得约契报太子；\n左右杀轲，刺秦失败。\n\n《史记》主要记载见[[086_刺客列传|086 刺客列传]]。\n\n---\n\n## 生平\n\n### 易水送别 · 风萧萧兮\n\n太子丹患秦进逼，荆轲请得樊於期首级与燕督亢地图——\n\n> 太子及宾客知其事者，皆白衣冠以送之。至易水之上，既祖，取道，高渐离击筑，荆轲和而歌，为变徵之声，士皆垂泪涕泣。又前而为歌曰：\"风萧萧兮易水寒，壮士一去兮不复还！\"复为羽声慷慨，士皆瞋目，发尽上指冠。於是荆轲就车而去，终已不顾。（[[086_刺客列传|086-034]]）\n\n### 图穷匕见 · 倚柱而笑\n\n至秦，以地图献秦王——\n\n> 荆轲奉樊於期头函，而秦舞阳奉地图柙，以次进。至陛，秦舞阳色变振恐……轲既取图奏之，秦王发图，图穷而匕首见。因左手把秦王之袖，而右手持匕首揕之。未至身，秦王惊，自引而起，袖绝。（[[086_刺客列传|086-035]]）\n\n秦王环柱而走，群臣惶急失度，侍医夏无且以药囊投荆轲——秦王负剑拔之，断荆轲左股。\n\n> 轲自知事不就，倚柱而笑，箕踞以骂曰：\"事所以不成者，以欲生劫之，必得约契以报太子也。\"於是左右既前杀轲，秦王不怡者良久。（[[086_刺客列传|086-035]]）\n\n---\n\n## 太史公曰\n\n> 太史公曰：自曹沫至荆轲五人，此其义或成或不成，然其立意较然，不欺其志，名垂後世，岂妄也哉！（[[086_刺客列传|086-039]]）\n\n---\n\n## 对照表\n\n| 项目 | 内容 |\n| --- | --- |\n| 籍贯 | 卫（先祖为齐人，徙卫） |\n| 卒年 | 前 227 年（刺秦失败，被杀于咸阳宫） |\n| 关键事迹 | 易水送别、图穷匕见、倚柱骂曰 |\n| 主要传记 | [[086_刺客列传|086 刺客列传]] |\n\n---\n\n## 典故与成语\n\n- **图穷匕见** — 地图展开尽头，匕首显现；比喻阴谋败露\n- **风萧萧兮易水寒** — 千古悲歌，壮士诀别之词\n- **荆轲刺秦** — 中国历史上最著名的刺杀行动\n\n---\n\n## 相关章节\n\n- [[086_刺客列传|086 刺客列传]]（主要出处，含曹沫、专诸、豫让、聂政、荆轲）\n\n## 相关人物\n\n- 高渐离（挚友，击筑送行，后以筑击秦始皇）\n- 燕太子丹（主君，礼遇荆轲）\n- 樊於期（自刭献首，成全荆轲计划）\n\n---\n\n*外部索引*: [person.html#荆轲](../../docs/entities/person.html#荆轲)\n",
      "size_before": 0
    }
  ]
}
