{
  "page": "蕞",
  "latest_rev_id": "20260424-070412-466ccc",
  "revision_count": 1,
  "revisions": [
    {
      "rev_id": "20260424-070412-466ccc",
      "timestamp": "2026-04-24T07:04:12Z",
      "author": "butler",
      "summary": "butler/import-places: 新建地名页",
      "parent_rev": null,
      "content_hash": "sha256:466ccc06bb6e52b3c5b2eafa4f8a5f29e8bf745e798d56c925d3754f12a31ec8",
      "size": 435,
      "content": "---\nid: 蕞\ntype: place\nlabel: 蕞\naliases: []\ntags: [\"地名\", \"城邑\"]\nauto_generated: true\n---\n\n# 蕞\n\n## 史记引文\n\n《史记》中出现 **1** 次，见于以下章节：\n\n[[043_赵世家]]\n\n**引文摘录：**\n\n出自 [[043_赵世家]]：\n> 将，攻燕，禽其将剧辛。四年，庞暖将赵、楚、魏、燕之锐师，攻秦蕞，不拔；移攻齐，取饶安。五年，傅抵将，居平邑；庆舍将东阳河外\n"
    }
  ]
}
