{
  "page": "越繇王",
  "latest_rev_id": "20260425-145501-3862b7",
  "revision_count": 4,
  "revisions": [
    {
      "rev_id": "20260425-145501-3862b7",
      "timestamp": "2026-04-25T14:55:01Z",
      "author": "butler",
      "summary": "H2: 从sources推导相关章节节",
      "parent_rev": "20260425-132345-3e84f2",
      "content_hash": "sha256:3862b730d17dde1fe2145f354472a396cc389eeb32e0358fff7cc0cc32400f18",
      "size": 861,
      "content": "---\nid: 越繇王\ntype: person\nlabel: 越繇王\nsources: [晋世家]\ndescription: 《史记》中出现 1 处（标注符号：〖@越繇王〗）\naliases: [\"丑\"]\ncanonical_name: 越繇王\ntags: [史记人物, 诸侯君主]\nfeatured: false\n---\n# 越繇王\n\n出现于《史记》**1** 处。\n\n## 史记引文\n\n《史记》中出现 **1** 处（标注符号：〖@越繇王〗）。\n\n**章节分布：**\n\n- [[039_晋世家|晋世家]]：（039-33）\n\n**引文摘录：**\n\n> 出自 [[039_晋世家|晋世家]] （039-33）：是岁也，晋复假道於虞以伐虢。 虞之大夫宫之奇谏虞君曰：“晋不可假道也，是且灭虞。” 虞君曰：“晋我同姓，不宜伐我。” 宫之奇曰：“太伯、虞仲，太王之子也，太伯亡去，是以不嗣。虢仲、…\n\n## 相关页面\n\n---\n\n## 相关章节\n\n- [[039_晋世家|晋世家]]\n"
    },
    {
      "rev_id": "20260425-132345-3e84f2",
      "timestamp": "2026-04-25T13:23:45Z",
      "author": "butler",
      "summary": "H8: 添加「史记人物」tag",
      "parent_rev": "20260425-131220-7de718",
      "content_hash": "sha256:3e84f2f21150c0b8a950991343956b5b686a9461ea879672a65582f2657995a1",
      "size": 793,
      "content": "---\nid: 越繇王\ntype: person\nlabel: 越繇王\nsources: [晋世家]\ndescription: 《史记》中出现 1 处（标注符号：〖@越繇王〗）\naliases: [\"丑\"]\ncanonical_name: 越繇王\ntags: [史记人物, 诸侯君主]\nfeatured: false\n---\n# 越繇王\n\n出现于《史记》**1** 处。\n\n## 史记引文\n\n《史记》中出现 **1** 处（标注符号：〖@越繇王〗）。\n\n**章节分布：**\n\n- [[039_晋世家|晋世家]]：§33\n\n**引文摘录：**\n\n> 出自 [[039_晋世家|晋世家]] §33：是岁也，晋复假道於虞以伐虢。 虞之大夫宫之奇谏虞君曰：“晋不可假道也，是且灭虞。” 虞君曰：“晋我同姓，不宜伐我。” 宫之奇曰：“太伯、虞仲，太王之子也，太伯亡去，是以不嗣。虢仲、…\n\n## 相关页面\n\n"
    },
    {
      "rev_id": "20260425-131220-7de718",
      "timestamp": "2026-04-25T13:12:20Z",
      "author": "butler",
      "summary": "H4: 从wikilinks推导sources",
      "parent_rev": "20260425-124623-743461",
      "content_hash": "sha256:7de718dbc63e73a0f2f0dbbed0a15473cfd56a201ef8c58b4b7f88ae6ea6396a",
      "size": 781,
      "content": "---\nid: 越繇王\ntype: person\nlabel: 越繇王\nsources: [晋世家]\ndescription: 《史记》中出现 1 处（标注符号：〖@越繇王〗）\naliases: [\"丑\"]\ncanonical_name: 越繇王\ntags: [\"诸侯君主\"]\nfeatured: false\n---\n# 越繇王\n\n出现于《史记》**1** 处。\n\n## 史记引文\n\n《史记》中出现 **1** 处（标注符号：〖@越繇王〗）。\n\n**章节分布：**\n\n- [[039_晋世家|晋世家]]：§33\n\n**引文摘录：**\n\n> 出自 [[039_晋世家|晋世家]] §33：是岁也，晋复假道於虞以伐虢。 虞之大夫宫之奇谏虞君曰：“晋不可假道也，是且灭虞。” 虞君曰：“晋我同姓，不宜伐我。” 宫之奇曰：“太伯、虞仲，太王之子也，太伯亡去，是以不嗣。虢仲、…\n\n## 相关页面\n\n"
    },
    {
      "rev_id": "20260425-124623-743461",
      "timestamp": "2026-04-25T12:46:23Z",
      "author": "butler",
      "summary": "H4: 添加 description 字段（首段推导）",
      "parent_rev": null,
      "content_hash": "sha256:7434611dc82c4594be7b7f91b52e6c481eec11ff4d2a6d4feacf06f6b12917f2",
      "size": 761,
      "content": "---\nid: 越繇王\ntype: person\nlabel: 越繇王\ndescription: 《史记》中出现 1 处（标注符号：〖@越繇王〗）\naliases: [\"丑\"]\ncanonical_name: 越繇王\ntags: [\"诸侯君主\"]\nfeatured: false\n---\n\n# 越繇王\n\n出现于《史记》**1** 处。\n\n## 史记引文\n\n《史记》中出现 **1** 处（标注符号：〖@越繇王〗）。\n\n**章节分布：**\n\n- [[039_晋世家|晋世家]]：§33\n\n**引文摘录：**\n\n> 出自 [[039_晋世家|晋世家]] §33：是岁也，晋复假道於虞以伐虢。 虞之大夫宫之奇谏虞君曰：“晋不可假道也，是且灭虞。” 虞君曰：“晋我同姓，不宜伐我。” 宫之奇曰：“太伯、虞仲，太王之子也，太伯亡去，是以不嗣。虢仲、…\n\n## 相关页面\n\n"
    }
  ]
}
