{
  "page": "陈平",
  "latest_rev_id": "20260422-172449-f2f4aa",
  "revision_count": 4,
  "revisions": [
    {
      "rev_id": "20260422-172449-f2f4aa",
      "timestamp": "2026-04-22T17:24:49+08:00",
      "author": "butler",
      "summary": "butler/cite-doc-report: 陈平",
      "parent_rev": "20260422-164320-4eb3f6",
      "content_hash": "sha256:f2f4aa6751df6eddcf1f991077fcb13350b5dd503abfbcb3bd67f9f686f2fb98",
      "size": 610
    },
    {
      "rev_id": "20260422-164320-4eb3f6",
      "timestamp": "2026-04-22T16:43:20+08:00",
      "author": "butler",
      "summary": "butler/add-tag: 陈平",
      "parent_rev": "20260422-081300-4232fc",
      "content_hash": "sha256:4eb3f6d1b805d3a1a52adf450c9c3711b748e877356a4471ef2f4c3a4b72cedd",
      "size": 550
    },
    {
      "rev_id": "20260422-081300-4232fc",
      "timestamp": "2026-04-22T08:13:00+00:00",
      "author": "butler",
      "summary": "butler/create-stub: 陈平 P1 queue, refs=66/17",
      "parent_rev": "20260422-160858-b96922",
      "content_hash": "sha256:4232fc90c1527a808b080affa7013a8b35bec01fd8c518d614452cd1f0402151",
      "size": 514
    },
    {
      "rev_id": "20260422-160858-b96922",
      "timestamp": "2026-04-22T16:08:58+08:00",
      "author": "migration",
      "summary": "initial import from docs/wiki/pages/",
      "parent_rev": null,
      "content_hash": "sha256:b96922b830545c159b9a54337f1e77f68fc7d1caf87cdc4b055462004bc94b6f",
      "size": 1534
    }
  ]
}
