{
  "page": "除田半租立太宗庙",
  "latest_rev_id": "20260423-155555-e81a0f",
  "revision_count": 1,
  "revisions": [
    {
      "rev_id": "20260423-155555-e81a0f",
      "timestamp": "2026-04-23T15:55:55Z",
      "author": "butler",
      "summary": "butler/import-event: 除田半租立太宗庙 新建 (011-003)",
      "parent_rev": null,
      "content_hash": "sha256:e81a0fc394ae2485a9c66ec9adde12dabd640b3ec7e30b9fd7326d395b8b817e",
      "size": 599,
      "content": "---\nid: \"除田半租立太宗庙\"\ntype: event\ntitle: 除田半租立太宗庙\ndescription: 五月除田半租，为孝文帝立太宗庙，令群臣无朝贺。\ntags: [史记, 事件, 孝景本纪]\nsources: [孝景本纪]\nevent_ids: [011-003]\ndate: \"〖%五月〗 （公元前156年）\"\n---\n\n# 除田半租立太宗庙\n\n> 五月除田半租，为孝文帝立太宗庙，令群臣无朝贺。\n\n**主要人物**：孝景皇帝\n\n## 事件经过\n\n五月除田半租，为孝文帝立太宗庙，令群臣无朝贺。\n\n## 原文\n\n> 五月，除田半租，为孝文立太宗庙。令群臣无朝贺。\n\n"
    }
  ]
}
