{
  "page": "青臣",
  "latest_rev_id": "20260425-132809-10b1f3",
  "revision_count": 5,
  "revisions": [
    {
      "rev_id": "20260425-132809-10b1f3",
      "timestamp": "2026-04-25T13:28:09Z",
      "author": "butler",
      "summary": "H8: 修复重复tags字段",
      "parent_rev": "20260425-131622-0339dc",
      "content_hash": "sha256:10b1f3a79e5a13fe3a6a6498272bf7ee5770600845c5d2c47998e881441085e8",
      "size": 721,
      "content": "---\nid: 青臣\ntype: person\nlabel: 青臣\nsources: [秦始皇本纪]\ndescription: 《史记》中出现 1 处（标注符号：〖@青臣〗）\ntags: [史记人物, 秦国]\naliases: []\ncanonical_name: 青臣\nfeatured: false\n---\n# 青臣\n\n出现于《史记》**1** 处。\n\n## 史记引文\n\n《史记》中出现 **1** 处（标注符号：〖@青臣〗）。\n\n**章节分布：**\n\n- [[006_秦始皇本纪|秦始皇本纪]]：§62.1\n\n**引文摘录：**\n\n> 出自 [[006_秦始皇本纪|秦始皇本纪]] §62.1：…，而子弟为匹夫，卒有田常、六卿之臣，无辅拂，何以相救哉？事不师古而能长久者，非所闻也。今**青臣**又面谀以重陛下之过，非忠臣。”\n\n## 相关页面\n\n"
    },
    {
      "rev_id": "20260425-131622-0339dc",
      "timestamp": "2026-04-25T13:16:22Z",
      "author": "butler",
      "summary": "H8: 添加基础tags（史记人物/时代）",
      "parent_rev": "20260425-131258-9d80cd",
      "content_hash": "sha256:0339dc07be0ec1a11fc5cfaa4fd1d83f97c3bafd78441912fe81722cb1949c75",
      "size": 730,
      "content": "---\nid: 青臣\ntype: person\nlabel: 青臣\nsources: [秦始皇本纪]\ndescription: 《史记》中出现 1 处（标注符号：〖@青臣〗）\ntags: [史记人物, 秦国]\naliases: []\ncanonical_name: 青臣\ntags: []\nfeatured: false\n---\n# 青臣\n\n出现于《史记》**1** 处。\n\n## 史记引文\n\n《史记》中出现 **1** 处（标注符号：〖@青臣〗）。\n\n**章节分布：**\n\n- [[006_秦始皇本纪|秦始皇本纪]]：§62.1\n\n**引文摘录：**\n\n> 出自 [[006_秦始皇本纪|秦始皇本纪]] §62.1：…，而子弟为匹夫，卒有田常、六卿之臣，无辅拂，何以相救哉？事不师古而能长久者，非所闻也。今**青臣**又面谀以重陛下之过，非忠臣。”\n\n## 相关页面\n\n"
    },
    {
      "rev_id": "20260425-131258-9d80cd",
      "timestamp": "2026-04-25T13:12:58Z",
      "author": "butler",
      "summary": "H4: 从wikilinks推导sources",
      "parent_rev": "20260425-124722-9c896f",
      "content_hash": "sha256:9d80cdefb2e142b4e6c1e8f69a85a63cefbed1db77c8e922d1cd19c2e1295ba1",
      "size": 701,
      "content": "---\nid: 青臣\ntype: person\nlabel: 青臣\nsources: [秦始皇本纪]\ndescription: 《史记》中出现 1 处（标注符号：〖@青臣〗）\naliases: []\ncanonical_name: 青臣\ntags: []\nfeatured: false\n---\n# 青臣\n\n出现于《史记》**1** 处。\n\n## 史记引文\n\n《史记》中出现 **1** 处（标注符号：〖@青臣〗）。\n\n**章节分布：**\n\n- [[006_秦始皇本纪|秦始皇本纪]]：§62.1\n\n**引文摘录：**\n\n> 出自 [[006_秦始皇本纪|秦始皇本纪]] §62.1：…，而子弟为匹夫，卒有田常、六卿之臣，无辅拂，何以相救哉？事不师古而能长久者，非所闻也。今**青臣**又面谀以重陛下之过，非忠臣。”\n\n## 相关页面\n\n"
    },
    {
      "rev_id": "20260425-124722-9c896f",
      "timestamp": "2026-04-25T12:47:22Z",
      "author": "butler",
      "summary": "H4: 添加 description 字段（首段推导）",
      "parent_rev": "20260425-122415-255fb7",
      "content_hash": "sha256:9c896ff2452b49a1cad1505dc01dc9a7eb1ba16782c5949ea4844352d7ef4094",
      "size": 675,
      "content": "---\nid: 青臣\ntype: person\nlabel: 青臣\ndescription: 《史记》中出现 1 处（标注符号：〖@青臣〗）\naliases: []\ncanonical_name: 青臣\ntags: []\nfeatured: false\n---\n\n# 青臣\n\n出现于《史记》**1** 处。\n\n## 史记引文\n\n《史记》中出现 **1** 处（标注符号：〖@青臣〗）。\n\n**章节分布：**\n\n- [[006_秦始皇本纪|秦始皇本纪]]：§62.1\n\n**引文摘录：**\n\n> 出自 [[006_秦始皇本纪|秦始皇本纪]] §62.1：…，而子弟为匹夫，卒有田常、六卿之臣，无辅拂，何以相救哉？事不师古而能长久者，非所闻也。今**青臣**又面谀以重陛下之过，非忠臣。”\n\n## 相关页面\n\n"
    },
    {
      "rev_id": "20260425-122415-255fb7",
      "timestamp": "2026-04-25T12:24:15Z",
      "author": "butler",
      "summary": "butler/import-person: 新建人名页面 青臣",
      "parent_rev": null,
      "content_hash": "sha256:255fb7fffae1abd85fc02bb2f6caba31b5b2f81355c913c702299a1591c74c59",
      "size": 600,
      "content": "---\nid: 青臣\ntype: person\nlabel: 青臣\naliases: []\ncanonical_name: 青臣\ntags: []\nfeatured: false\n---\n\n# 青臣\n\n出现于《史记》**1** 处。\n\n## 史记引文\n\n《史记》中出现 **1** 处（标注符号：〖@青臣〗）。\n\n**章节分布：**\n\n- [[006_秦始皇本纪|秦始皇本纪]]：§62.1\n\n**引文摘录：**\n\n> 出自 [[006_秦始皇本纪|秦始皇本纪]] §62.1：…，而子弟为匹夫，卒有田常、六卿之臣，无辅拂，何以相救哉？事不师古而能长久者，非所闻也。今**青臣**又面谀以重陛下之过，非忠臣。”\n\n## 相关页面\n\n"
    }
  ]
}
