{
  "page": "齐王尊稷下先生",
  "latest_rev_id": "20260423-154831-a57b0e",
  "revision_count": 1,
  "revisions": [
    {
      "rev_id": "20260423-154831-a57b0e",
      "timestamp": "2026-04-23T15:48:31Z",
      "author": "butler",
      "summary": "butler/import-event: 齐王尊稷下先生 新建 (074-007)",
      "parent_rev": null,
      "content_hash": "sha256:a57b0e30850b543e2833c38bf0911d4d0e60567cfff42a54f1f3b2f655967a81",
      "size": 965,
      "content": "---\nid: \"齐王尊稷下先生\"\ntype: event\ntitle: 齐王尊稷下先生\ndescription: 齐王嘉赏稷下学者，自淳于髡以下皆命为列大夫，开第于康庄大衢，高门大屋以示尊宠。以此向天下诸侯展示齐国能招致天下贤士。\ntags: [史记, 事件, 孟子荀卿列传]\nsources: [孟子荀卿列传]\nevent_ids: [074-007]\ndate: \"[约公元前356—前301年]\"\n---\n\n# 齐王尊稷下先生\n\n> 齐王嘉赏稷下学者，自淳于髡以下皆命为列大夫，开第于康庄大衢，高门大屋以示尊宠。以此向天下诸侯展示齐国能招致天下贤士。\n\n**主要人物**：淳于髡、齐王\n\n## 事件经过\n\n齐王嘉赏稷下学者，自淳于髡以下皆命为列大夫，开第于康庄大衢，高门大屋以示尊宠。以此向天下诸侯展示齐国能招致天下贤士。\n\n## 原文\n\n> 於是齐王嘉之，自如淳于髡以下，皆命曰列大夫，为开第康庄之衢，高门大屋，尊宠之。\n\n"
    }
  ]
}
