{
  "chapter_id": "071",
  "total_events": 21,
  "corrections": [
    {
      "event_id": "071-001",
      "current_year": "（公元前329年）/ [公元前330年]",
      "suggested_year": "（公元前329年）",
      "reason": "概览表标注（公元前329年）正确，但详情中公元纪年行标注[公元前330年]与之不一致（错误模式6格式不一致）。年表前329年条记载秦取曲沃，应统一为（公元前329年）",
      "confidence": "high"
    },
    {
      "event_id": "071-005",
      "current_year": "[公元前310—前309年] [公元前310—前309年] [公元前310—前309年] [公元前310—前309年]",
      "suggested_year": "[公元前310—前309年]",
      "reason": "时间字段四重重复标注（错误模式28/33），应清理为单一标注",
      "confidence": "high"
    },
    {
      "event_id": "071-007",
      "current_year": "[公元前307年]",
      "suggested_year": "（公元前307年）",
      "reason": "确定性标注不足（错误模式7）：年表前307年条明确记载武王卒、昭王立，应升级为精确纪年",
      "confidence": "high"
    },
    {
      "event_id": "071-011",
      "current_year": "[约公元前310年]",
      "suggested_year": "（公元前310年）",
      "reason": "确定性标注不足（错误模式7）：年表前310年条记载杀蜀相壮，应升级为精确纪年",
      "confidence": "high"
    },
    {
      "event_id": "071-012",
      "current_year": "[约公元前309年]",
      "suggested_year": "（公元前309年）",
      "reason": "确定性标注不足（错误模式7）：年表前309年条记载初置丞相，应升级为精确纪年",
      "confidence": "high"
    },
    {
      "event_id": "071-014",
      "current_year": "[约公元前306年]",
      "suggested_year": "（公元前306年）",
      "reason": "确定性标注不足（错误模式7）：年表前306年秦昭王元年相关事件吻合，应升级为精确纪年",
      "confidence": "high"
    },
    {
      "event_id": "071-015",
      "current_year": "[公元前307年]",
      "suggested_year": "（公元前307年）",
      "reason": "确定性标注不足（错误模式7）：年表前307年条明确记载武王卒于周，应升级为精确纪年",
      "confidence": "high"
    },
    {
      "event_id": "071-016",
      "current_year": "[约公元前306年]",
      "suggested_year": "（公元前306年）",
      "reason": "确定性标注不足（错误模式7）：年表前306年条记载甘茂逃齐，应升级为精确纪年",
      "confidence": "high"
    }
  ],
  "cross_chapter_checks": [
    {
      "event": "秦取曲沃",
      "this_chapter": "071-001 （公元前329年）",
      "other_chapter": "005_秦本纪 前329年",
      "consistent": true
    },
    {
      "event": "武王卒昭王立",
      "this_chapter": "071-015 [公元前307年]",
      "other_chapter": "005_秦本纪 前307年",
      "consistent": true
    }
  ],
  "new_patterns": [],
  "notes": "第五轮跨章节交叉验证。071章21个事件，主要问题仍是确定性标注不足（6处升级）和重复标注（1处）。071-001详情中公元纪年行与概览表不一致需统一。跨章节验证与005秦本纪一致，无冲突。"
}